{
  "track_reged_mode" : 1,
  "num_output_ib" : 1,
  "connection_format" : [ "src_id", "src_type", "src_out_idx", "dst_id", "dst_type", "dst_in_idx" ],
  "num_rf_reg" : 1,
  "num_input_ob" : 2,
  "num_row" : 9,
  "operations" : [ "PASS", "ADD", "SUB", "MUL", "AND", "OR", "XOR" ],
  "cfg_data_width" : 32,
  "pin_2_track_connection" : {
    "connect_2_side2" : true,
    "connect_2_side4" : false,
    "connect_2_side1" : false,
    "connect_2_side3" : true
  },
  "num_mem_perin" : 1,
  "num_output" : 8,
  "max_II" : 1,
  "num_mem_out" : 1,
  "cfg_addr_width" : 14,
  "num_input_ib" : 1,
  "memory_depth_percycle" : 64,
  "num_track" : 1,
  "data_width" : 32,
  "num_colum" : 4,
  "top_module" : "CGRA",
  "sub_modules" : [ {
    "type" : "GIB",
    "attributes" : {
      "pin_2_track_connection" : {
        "connect_2_side2" : true,
        "connect_2_side4" : false,
        "connect_2_side1" : false,
        "connect_2_side3" : true
      },
      "cfg_data_width" : 32,
      "num_output" : 8,
      "max_II" : 1,
      "cfg_addr_width" : 14,
      "data_width" : 32,
      "y" : 1,
      "num_track" : 1,
      "sub_modules" : [ {
        "id" : 1,
        "type" : "Muxn"
      } ],
      "cfg_blk_offset" : 2,
      "x" : 2,
      "pin_2_pin_connection" : {
        "connect_2_side2" : false,
        "connect_2_side1" : true,
        "connect_2_side3" : true
      },
      "configuration" : {
        "8" : [ "Muxn", 17, 16 ],
        "2" : [ "Muxn", 3, 2 ],
        "5" : [ "Muxn", 10, 8 ],
        "4" : [ "Muxn", 7, 6 ],
        "7" : [ "Muxn", 15, 14 ],
        "1" : [ "Muxn", 1, 0 ],
        "3" : [ "Muxn", 5, 4 ],
        "6" : [ "Muxn", 13, 11 ],
        "0" : [ "This", 17, 0 ]
      },
      "instances" : [ {
        "id" : 0,
        "type" : "This",
        "module_id" : 0
      }, {
        "id" : 1,
        "type" : "Muxn",
        "module_id" : 1
      }, {
        "id" : 2,
        "type" : "Muxn",
        "module_id" : 1
      }, {
        "id" : 3,
        "type" : "Muxn",
        "module_id" : 1
      }, {
        "id" : 4,
        "type" : "Muxn",
        "module_id" : 1
      }, {
        "id" : 5,
        "type" : "Muxn",
        "module_id" : 1
      }, {
        "id" : 6,
        "type" : "Muxn",
        "module_id" : 1
      }, {
        "id" : 7,
        "type" : "Muxn",
        "module_id" : 1
      }, {
        "id" : 8,
        "type" : "Muxn",
        "module_id" : 1
      } ],
      "connect_flexibility" : {
        "num_perside_ipin_per_opin" : 1,
        "num_perside_otrack_per_opin" : 1,
        "num_perside_itrack_per_ipin" : 1
      },
      "num_input" : 7,
      "track_reged" : false,
      "connections" : {
        "0" : [ 0, "This", 5, 1, "Muxn", 0 ],
        "5" : [ 0, "This", 0, 2, "Muxn", 1 ],
        "10" : [ 0, "This", 1, 3, "Muxn", 2 ],
        "24" : [ 0, "This", 0, 6, "Muxn", 2 ],
        "37" : [ 8, "Muxn", 0, 0, "This", 3 ],
        "25" : [ 0, "This", 2, 6, "Muxn", 3 ],
        "14" : [ 0, "This", 2, 4, "Muxn", 2 ],
        "20" : [ 0, "This", 3, 5, "Muxn", 4 ],
        "29" : [ 0, "This", 0, 7, "Muxn", 1 ],
        "1" : [ 0, "This", 0, 1, "Muxn", 1 ],
        "6" : [ 0, "This", 1, 2, "Muxn", 2 ],
        "28" : [ 0, "This", 6, 7, "Muxn", 0 ],
        "21" : [ 5, "Muxn", 0, 0, "This", 0 ],
        "33" : [ 0, "This", 4, 8, "Muxn", 0 ],
        "9" : [ 0, "This", 0, 3, "Muxn", 1 ],
        "13" : [ 0, "This", 1, 4, "Muxn", 1 ],
        "2" : [ 0, "This", 3, 1, "Muxn", 2 ],
        "32" : [ 7, "Muxn", 0, 0, "This", 2 ],
        "34" : [ 0, "This", 0, 8, "Muxn", 1 ],
        "17" : [ 0, "This", 5, 5, "Muxn", 1 ],
        "22" : [ 0, "This", 5, 6, "Muxn", 0 ],
        "27" : [ 6, "Muxn", 0, 0, "This", 1 ],
        "12" : [ 0, "This", 5, 4, "Muxn", 0 ],
        "7" : [ 2, "Muxn", 0, 0, "This", 5 ],
        "3" : [ 1, "Muxn", 0, 0, "This", 4 ],
        "35" : [ 0, "This", 1, 8, "Muxn", 2 ],
        "18" : [ 0, "This", 1, 5, "Muxn", 2 ],
        "16" : [ 0, "This", 4, 5, "Muxn", 0 ],
        "31" : [ 0, "This", 3, 7, "Muxn", 3 ],
        "11" : [ 3, "Muxn", 0, 0, "This", 6 ],
        "26" : [ 0, "This", 3, 6, "Muxn", 4 ],
        "23" : [ 0, "This", 6, 6, "Muxn", 1 ],
        "8" : [ 0, "This", 4, 3, "Muxn", 0 ],
        "36" : [ 0, "This", 2, 8, "Muxn", 3 ],
        "30" : [ 0, "This", 1, 7, "Muxn", 2 ],
        "19" : [ 0, "This", 2, 5, "Muxn", 3 ],
        "4" : [ 0, "This", 6, 2, "Muxn", 0 ],
        "15" : [ 4, "Muxn", 0, 0, "This", 7 ]
      },
      "cfg_blk_index" : 13,
      "num_iopin_list" : {
        "opin_ne" : 1,
        "opin_nw" : 0,
        "opin_sw" : 1,
        "opin_se" : 1,
        "ipin_ne" : 1,
        "ipin_nw" : 0,
        "ipin_sw" : 1,
        "ipin_se" : 2
      }
    },
    "id" : 4
  }, {
    "type" : "GIB",
    "attributes" : {
      "pin_2_track_connection" : {
        "connect_2_side2" : true,
        "connect_2_side4" : false,
        "connect_2_side1" : false,
        "connect_2_side3" : true
      },
      "cfg_data_width" : 32,
      "num_output" : 10,
      "max_II" : 1,
      "cfg_addr_width" : 14,
      "data_width" : 32,
      "y" : 3,
      "num_track" : 1,
      "sub_modules" : [ {
        "id" : 1,
        "type" : "Muxn"
      } ],
      "cfg_blk_offset" : 2,
      "x" : 2,
      "pin_2_pin_connection" : {
        "connect_2_side2" : false,
        "connect_2_side1" : true,
        "connect_2_side3" : true
      },
      "configuration" : {
        "8" : [ "Muxn", 17, 15 ],
        "2" : [ "Muxn", 3, 2 ],
        "5" : [ "Muxn", 9, 8 ],
        "4" : [ "Muxn", 7, 6 ],
        "7" : [ "Muxn", 14, 12 ],
        "10" : [ "Muxn", 23, 21 ],
        "1" : [ "Muxn", 1, 0 ],
        "9" : [ "Muxn", 20, 18 ],
        "3" : [ "Muxn", 5, 4 ],
        "6" : [ "Muxn", 11, 10 ],
        "0" : [ "This", 23, 0 ]
      },
      "instances" : [ {
        "id" : 0,
        "type" : "This",
        "module_id" : 0
      }, {
        "id" : 1,
        "type" : "Muxn",
        "module_id" : 1
      }, {
        "id" : 2,
        "type" : "Muxn",
        "module_id" : 1
      }, {
        "id" : 3,
        "type" : "Muxn",
        "module_id" : 1
      }, {
        "id" : 4,
        "type" : "Muxn",
        "module_id" : 1
      }, {
        "id" : 5,
        "type" : "Muxn",
        "module_id" : 1
      }, {
        "id" : 6,
        "type" : "Muxn",
        "module_id" : 1
      }, {
        "id" : 7,
        "type" : "Muxn",
        "module_id" : 1
      }, {
        "id" : 8,
        "type" : "Muxn",
        "module_id" : 1
      }, {
        "id" : 9,
        "type" : "Muxn",
        "module_id" : 1
      }, {
        "id" : 10,
        "type" : "Muxn",
        "module_id" : 1
      } ],
      "connect_flexibility" : {
        "num_perside_ipin_per_opin" : 1,
        "num_perside_otrack_per_opin" : 1,
        "num_perside_itrack_per_ipin" : 1
      },
      "num_input" : 8,
      "track_reged" : true,
      "connections" : {
        "0" : [ 0, "This", 5, 1, "Muxn", 0 ],
        "5" : [ 0, "This", 4, 2, "Muxn", 0 ],
        "10" : [ 0, "This", 7, 3, "Muxn", 0 ],
        "42" : [ 0, "This", 3, 9, "Muxn", 4 ],
        "24" : [ 0, "This", 2, 6, "Muxn", 2 ],
        "37" : [ 8, "Muxn", 0, 0, "This", 1 ],
        "25" : [ 6, "Muxn", 0, 0, "This", 9 ],
        "14" : [ 0, "This", 5, 4, "Muxn", 0 ],
        "20" : [ 0, "This", 2, 5, "Muxn", 2 ],
        "46" : [ 0, "This", 0, 10, "Muxn", 2 ],
        "29" : [ 0, "This", 2, 7, "Muxn", 3 ],
        "1" : [ 0, "This", 7, 1, "Muxn", 1 ],
        "6" : [ 0, "This", 6, 2, "Muxn", 1 ],
        "28" : [ 0, "This", 1, 7, "Muxn", 2 ],
        "38" : [ 0, "This", 4, 9, "Muxn", 0 ],
        "21" : [ 5, "Muxn", 0, 0, "This", 8 ],
        "33" : [ 0, "This", 7, 8, "Muxn", 1 ],
        "9" : [ 2, "Muxn", 0, 0, "This", 5 ],
        "13" : [ 3, "Muxn", 0, 0, "This", 6 ],
        "41" : [ 0, "This", 1, 9, "Muxn", 3 ],
        "2" : [ 0, "This", 2, 1, "Muxn", 2 ],
        "32" : [ 0, "This", 6, 8, "Muxn", 0 ],
        "34" : [ 0, "This", 0, 8, "Muxn", 2 ],
        "45" : [ 0, "This", 5, 10, "Muxn", 1 ],
        "17" : [ 4, "Muxn", 0, 0, "This", 7 ],
        "22" : [ 0, "This", 4, 6, "Muxn", 0 ],
        "44" : [ 0, "This", 4, 10, "Muxn", 0 ],
        "27" : [ 0, "This", 6, 7, "Muxn", 1 ],
        "12" : [ 0, "This", 1, 3, "Muxn", 2 ],
        "49" : [ 10, "Muxn", 0, 0, "This", 3 ],
        "7" : [ 0, "This", 0, 2, "Muxn", 2 ],
        "39" : [ 0, "This", 7, 9, "Muxn", 1 ],
        "3" : [ 0, "This", 3, 1, "Muxn", 3 ],
        "35" : [ 0, "This", 2, 8, "Muxn", 3 ],
        "48" : [ 0, "This", 2, 10, "Muxn", 4 ],
        "18" : [ 0, "This", 6, 5, "Muxn", 0 ],
        "16" : [ 0, "This", 1, 4, "Muxn", 2 ],
        "31" : [ 7, "Muxn", 0, 0, "This", 0 ],
        "11" : [ 0, "This", 0, 3, "Muxn", 1 ],
        "43" : [ 9, "Muxn", 0, 0, "This", 2 ],
        "40" : [ 0, "This", 0, 9, "Muxn", 2 ],
        "26" : [ 0, "This", 5, 7, "Muxn", 0 ],
        "23" : [ 0, "This", 1, 6, "Muxn", 1 ],
        "8" : [ 0, "This", 3, 2, "Muxn", 3 ],
        "36" : [ 0, "This", 3, 8, "Muxn", 4 ],
        "30" : [ 0, "This", 3, 7, "Muxn", 4 ],
        "19" : [ 0, "This", 1, 5, "Muxn", 1 ],
        "4" : [ 1, "Muxn", 0, 0, "This", 4 ],
        "47" : [ 0, "This", 1, 10, "Muxn", 3 ],
        "15" : [ 0, "This", 0, 4, "Muxn", 1 ]
      },
      "cfg_blk_index" : 14,
      "num_iopin_list" : {
        "opin_ne" : 1,
        "opin_nw" : 1,
        "opin_sw" : 1,
        "opin_se" : 1,
        "ipin_ne" : 1,
        "ipin_nw" : 1,
        "ipin_sw" : 2,
        "ipin_se" : 2
      }
    },
    "id" : 5
  }, {
    "type" : "GIB",
    "attributes" : {
      "pin_2_track_connection" : {
        "connect_2_side2" : true,
        "connect_2_side4" : false,
        "connect_2_side1" : false,
        "connect_2_side3" : true
      },
      "cfg_data_width" : 32,
      "num_output" : 8,
      "max_II" : 1,
      "cfg_addr_width" : 14,
      "data_width" : 32,
      "y" : 9,
      "num_track" : 1,
      "sub_modules" : [ {
        "id" : 1,
        "type" : "Muxn"
      } ],
      "cfg_blk_offset" : 2,
      "x" : 2,
      "pin_2_pin_connection" : {
        "connect_2_side2" : false,
        "connect_2_side1" : true,
        "connect_2_side3" : true
      },
      "configuration" : {
        "8" : [ "Muxn", 17, 16 ],
        "2" : [ "Muxn", 3, 2 ],
        "5" : [ "Muxn", 9, 8 ],
        "4" : [ "Muxn", 7, 6 ],
        "7" : [ "Muxn", 15, 13 ],
        "1" : [ "Muxn", 1, 0 ],
        "3" : [ "Muxn", 5, 4 ],
        "6" : [ "Muxn", 12, 10 ],
        "0" : [ "This", 17, 0 ]
      },
      "instances" : [ {
        "id" : 0,
        "type" : "This",
        "module_id" : 0
      }, {
        "id" : 1,
        "type" : "Muxn",
        "module_id" : 1
      }, {
        "id" : 2,
        "type" : "Muxn",
        "module_id" : 1
      }, {
        "id" : 3,
        "type" : "Muxn",
        "module_id" : 1
      }, {
        "id" : 4,
        "type" : "Muxn",
        "module_id" : 1
      }, {
        "id" : 5,
        "type" : "Muxn",
        "module_id" : 1
      }, {
        "id" : 6,
        "type" : "Muxn",
        "module_id" : 1
      }, {
        "id" : 7,
        "type" : "Muxn",
        "module_id" : 1
      }, {
        "id" : 8,
        "type" : "Muxn",
        "module_id" : 1
      } ],
      "connect_flexibility" : {
        "num_perside_ipin_per_opin" : 1,
        "num_perside_otrack_per_opin" : 1,
        "num_perside_itrack_per_ipin" : 1
      },
      "num_input" : 7,
      "track_reged" : false,
      "connections" : {
        "0" : [ 0, "This", 6, 1, "Muxn", 0 ],
        "5" : [ 0, "This", 0, 2, "Muxn", 1 ],
        "10" : [ 0, "This", 2, 3, "Muxn", 2 ],
        "24" : [ 0, "This", 2, 6, "Muxn", 3 ],
        "37" : [ 8, "Muxn", 0, 0, "This", 3 ],
        "25" : [ 0, "This", 3, 6, "Muxn", 4 ],
        "14" : [ 0, "This", 2, 4, "Muxn", 2 ],
        "20" : [ 5, "Muxn", 0, 0, "This", 0 ],
        "29" : [ 0, "This", 0, 7, "Muxn", 2 ],
        "1" : [ 0, "This", 2, 1, "Muxn", 1 ],
        "6" : [ 0, "This", 1, 2, "Muxn", 2 ],
        "28" : [ 0, "This", 6, 7, "Muxn", 1 ],
        "21" : [ 0, "This", 5, 6, "Muxn", 0 ],
        "33" : [ 0, "This", 4, 8, "Muxn", 0 ],
        "9" : [ 0, "This", 1, 3, "Muxn", 1 ],
        "13" : [ 0, "This", 1, 4, "Muxn", 1 ],
        "2" : [ 0, "This", 3, 1, "Muxn", 2 ],
        "32" : [ 7, "Muxn", 0, 0, "This", 2 ],
        "34" : [ 0, "This", 0, 8, "Muxn", 1 ],
        "17" : [ 0, "This", 1, 5, "Muxn", 1 ],
        "22" : [ 0, "This", 6, 6, "Muxn", 1 ],
        "27" : [ 0, "This", 4, 7, "Muxn", 0 ],
        "12" : [ 0, "This", 4, 4, "Muxn", 0 ],
        "7" : [ 2, "Muxn", 0, 0, "This", 5 ],
        "3" : [ 1, "Muxn", 0, 0, "This", 4 ],
        "35" : [ 0, "This", 1, 8, "Muxn", 2 ],
        "18" : [ 0, "This", 2, 5, "Muxn", 2 ],
        "16" : [ 0, "This", 5, 5, "Muxn", 0 ],
        "31" : [ 0, "This", 3, 7, "Muxn", 4 ],
        "11" : [ 3, "Muxn", 0, 0, "This", 6 ],
        "26" : [ 6, "Muxn", 0, 0, "This", 1 ],
        "23" : [ 0, "This", 0, 6, "Muxn", 2 ],
        "8" : [ 0, "This", 5, 3, "Muxn", 0 ],
        "36" : [ 0, "This", 2, 8, "Muxn", 3 ],
        "30" : [ 0, "This", 1, 7, "Muxn", 3 ],
        "19" : [ 0, "This", 3, 5, "Muxn", 3 ],
        "4" : [ 0, "This", 6, 2, "Muxn", 0 ],
        "15" : [ 4, "Muxn", 0, 0, "This", 7 ]
      },
      "cfg_blk_index" : 17,
      "num_iopin_list" : {
        "opin_ne" : 0,
        "opin_nw" : 1,
        "opin_sw" : 1,
        "opin_se" : 1,
        "ipin_ne" : 0,
        "ipin_nw" : 1,
        "ipin_sw" : 2,
        "ipin_se" : 1
      }
    },
    "id" : 6
  }, {
    "type" : "GIB",
    "attributes" : {
      "pin_2_track_connection" : {
        "connect_2_side2" : true,
        "connect_2_side4" : false,
        "connect_2_side1" : false,
        "connect_2_side3" : true
      },
      "cfg_data_width" : 32,
      "num_output" : 10,
      "max_II" : 1,
      "cfg_addr_width" : 14,
      "data_width" : 32,
      "y" : 1,
      "num_track" : 1,
      "sub_modules" : [ {
        "id" : 1,
        "type" : "Muxn"
      } ],
      "cfg_blk_offset" : 2,
      "x" : 4,
      "pin_2_pin_connection" : {
        "connect_2_side2" : false,
        "connect_2_side1" : true,
        "connect_2_side3" : true
      },
      "configuration" : {
        "8" : [ "Muxn", 17, 15 ],
        "2" : [ "Muxn", 3, 2 ],
        "5" : [ "Muxn", 9, 8 ],
        "4" : [ "Muxn", 7, 6 ],
        "7" : [ "Muxn", 14, 12 ],
        "10" : [ "Muxn", 23, 21 ],
        "1" : [ "Muxn", 1, 0 ],
        "9" : [ "Muxn", 20, 18 ],
        "3" : [ "Muxn", 5, 4 ],
        "6" : [ "Muxn", 11, 10 ],
        "0" : [ "This", 23, 0 ]
      },
      "instances" : [ {
        "id" : 0,
        "type" : "This",
        "module_id" : 0
      }, {
        "id" : 1,
        "type" : "Muxn",
        "module_id" : 1
      }, {
        "id" : 2,
        "type" : "Muxn",
        "module_id" : 1
      }, {
        "id" : 3,
        "type" : "Muxn",
        "module_id" : 1
      }, {
        "id" : 4,
        "type" : "Muxn",
        "module_id" : 1
      }, {
        "id" : 5,
        "type" : "Muxn",
        "module_id" : 1
      }, {
        "id" : 6,
        "type" : "Muxn",
        "module_id" : 1
      }, {
        "id" : 7,
        "type" : "Muxn",
        "module_id" : 1
      }, {
        "id" : 8,
        "type" : "Muxn",
        "module_id" : 1
      }, {
        "id" : 9,
        "type" : "Muxn",
        "module_id" : 1
      }, {
        "id" : 10,
        "type" : "Muxn",
        "module_id" : 1
      } ],
      "connect_flexibility" : {
        "num_perside_ipin_per_opin" : 1,
        "num_perside_otrack_per_opin" : 1,
        "num_perside_itrack_per_ipin" : 1
      },
      "num_input" : 8,
      "track_reged" : true,
      "connections" : {
        "0" : [ 0, "This", 5, 1, "Muxn", 0 ],
        "5" : [ 0, "This", 4, 2, "Muxn", 0 ],
        "10" : [ 0, "This", 0, 3, "Muxn", 1 ],
        "42" : [ 0, "This", 3, 9, "Muxn", 4 ],
        "24" : [ 0, "This", 2, 6, "Muxn", 3 ],
        "37" : [ 8, "Muxn", 0, 0, "This", 1 ],
        "25" : [ 6, "Muxn", 0, 0, "This", 9 ],
        "14" : [ 0, "This", 0, 4, "Muxn", 1 ],
        "20" : [ 5, "Muxn", 0, 0, "This", 8 ],
        "46" : [ 0, "This", 0, 10, "Muxn", 2 ],
        "29" : [ 0, "This", 2, 7, "Muxn", 3 ],
        "1" : [ 0, "This", 7, 1, "Muxn", 1 ],
        "6" : [ 0, "This", 0, 2, "Muxn", 1 ],
        "28" : [ 0, "This", 1, 7, "Muxn", 2 ],
        "38" : [ 0, "This", 4, 9, "Muxn", 0 ],
        "21" : [ 0, "This", 4, 6, "Muxn", 0 ],
        "33" : [ 0, "This", 7, 8, "Muxn", 1 ],
        "9" : [ 0, "This", 6, 3, "Muxn", 0 ],
        "13" : [ 0, "This", 7, 4, "Muxn", 0 ],
        "41" : [ 0, "This", 1, 9, "Muxn", 3 ],
        "2" : [ 0, "This", 2, 1, "Muxn", 2 ],
        "32" : [ 0, "This", 6, 8, "Muxn", 0 ],
        "34" : [ 0, "This", 0, 8, "Muxn", 2 ],
        "45" : [ 0, "This", 5, 10, "Muxn", 1 ],
        "17" : [ 0, "This", 5, 5, "Muxn", 0 ],
        "22" : [ 0, "This", 6, 6, "Muxn", 1 ],
        "44" : [ 0, "This", 4, 10, "Muxn", 0 ],
        "27" : [ 0, "This", 6, 7, "Muxn", 1 ],
        "12" : [ 3, "Muxn", 0, 0, "This", 6 ],
        "49" : [ 10, "Muxn", 0, 0, "This", 3 ],
        "7" : [ 0, "This", 3, 2, "Muxn", 2 ],
        "39" : [ 0, "This", 7, 9, "Muxn", 1 ],
        "3" : [ 0, "This", 3, 1, "Muxn", 3 ],
        "35" : [ 0, "This", 2, 8, "Muxn", 3 ],
        "48" : [ 0, "This", 2, 10, "Muxn", 4 ],
        "18" : [ 0, "This", 0, 5, "Muxn", 1 ],
        "16" : [ 4, "Muxn", 0, 0, "This", 7 ],
        "31" : [ 7, "Muxn", 0, 0, "This", 0 ],
        "11" : [ 0, "This", 3, 3, "Muxn", 2 ],
        "43" : [ 9, "Muxn", 0, 0, "This", 2 ],
        "40" : [ 0, "This", 0, 9, "Muxn", 2 ],
        "26" : [ 0, "This", 5, 7, "Muxn", 0 ],
        "23" : [ 0, "This", 1, 6, "Muxn", 2 ],
        "8" : [ 2, "Muxn", 0, 0, "This", 5 ],
        "36" : [ 0, "This", 3, 8, "Muxn", 4 ],
        "30" : [ 0, "This", 3, 7, "Muxn", 4 ],
        "19" : [ 0, "This", 1, 5, "Muxn", 2 ],
        "4" : [ 1, "Muxn", 0, 0, "This", 4 ],
        "47" : [ 0, "This", 1, 10, "Muxn", 3 ],
        "15" : [ 0, "This", 1, 4, "Muxn", 2 ]
      },
      "cfg_blk_index" : 25,
      "num_iopin_list" : {
        "opin_ne" : 1,
        "opin_nw" : 1,
        "opin_sw" : 1,
        "opin_se" : 1,
        "ipin_ne" : 2,
        "ipin_nw" : 1,
        "ipin_sw" : 1,
        "ipin_se" : 2
      }
    },
    "id" : 7
  }, {
    "type" : "GIB",
    "attributes" : {
      "pin_2_track_connection" : {
        "connect_2_side2" : true,
        "connect_2_side4" : false,
        "connect_2_side1" : false,
        "connect_2_side3" : true
      },
      "cfg_data_width" : 32,
      "num_output" : 12,
      "max_II" : 1,
      "cfg_addr_width" : 14,
      "data_width" : 32,
      "y" : 3,
      "num_track" : 1,
      "sub_modules" : [ {
        "id" : 1,
        "type" : "Muxn"
      } ],
      "cfg_blk_offset" : 2,
      "x" : 4,
      "pin_2_pin_connection" : {
        "connect_2_side2" : false,
        "connect_2_side1" : true,
        "connect_2_side3" : true
      },
      "configuration" : {
        "8" : [ "Muxn", 15, 14 ],
        "11" : [ "Muxn", 24, 22 ],
        "2" : [ "Muxn", 3, 2 ],
        "5" : [ "Muxn", 9, 8 ],
        "4" : [ "Muxn", 7, 6 ],
        "7" : [ "Muxn", 13, 12 ],
        "1" : [ "Muxn", 1, 0 ],
        "10" : [ "Muxn", 21, 19 ],
        "9" : [ "Muxn", 18, 16 ],
        "3" : [ "Muxn", 5, 4 ],
        "12" : [ "Muxn", 27, 25 ],
        "6" : [ "Muxn", 11, 10 ],
        "0" : [ "This", 27, 0 ]
      },
      "instances" : [ {
        "id" : 0,
        "type" : "This",
        "module_id" : 0
      }, {
        "id" : 1,
        "type" : "Muxn",
        "module_id" : 1
      }, {
        "id" : 2,
        "type" : "Muxn",
        "module_id" : 1
      }, {
        "id" : 3,
        "type" : "Muxn",
        "module_id" : 1
      }, {
        "id" : 4,
        "type" : "Muxn",
        "module_id" : 1
      }, {
        "id" : 5,
        "type" : "Muxn",
        "module_id" : 1
      }, {
        "id" : 6,
        "type" : "Muxn",
        "module_id" : 1
      }, {
        "id" : 7,
        "type" : "Muxn",
        "module_id" : 1
      }, {
        "id" : 8,
        "type" : "Muxn",
        "module_id" : 1
      }, {
        "id" : 9,
        "type" : "Muxn",
        "module_id" : 1
      }, {
        "id" : 10,
        "type" : "Muxn",
        "module_id" : 1
      }, {
        "id" : 11,
        "type" : "Muxn",
        "module_id" : 1
      }, {
        "id" : 12,
        "type" : "Muxn",
        "module_id" : 1
      } ],
      "connect_flexibility" : {
        "num_perside_ipin_per_opin" : 1,
        "num_perside_otrack_per_opin" : 1,
        "num_perside_itrack_per_ipin" : 1
      },
      "num_input" : 8,
      "track_reged" : false,
      "connections" : {
        "0" : [ 0, "This", 5, 1, "Muxn", 0 ],
        "5" : [ 0, "This", 2, 2, "Muxn", 1 ],
        "10" : [ 0, "This", 3, 3, "Muxn", 2 ],
        "42" : [ 0, "This", 3, 10, "Muxn", 4 ],
        "24" : [ 0, "This", 6, 7, "Muxn", 0 ],
        "37" : [ 9, "Muxn", 0, 0, "This", 0 ],
        "25" : [ 0, "This", 1, 7, "Muxn", 1 ],
        "52" : [ 0, "This", 0, 12, "Muxn", 2 ],
        "14" : [ 0, "This", 3, 4, "Muxn", 2 ],
        "20" : [ 0, "This", 5, 6, "Muxn", 0 ],
        "46" : [ 0, "This", 0, 11, "Muxn", 2 ],
        "29" : [ 0, "This", 1, 8, "Muxn", 1 ],
        "1" : [ 0, "This", 2, 1, "Muxn", 1 ],
        "6" : [ 0, "This", 3, 2, "Muxn", 2 ],
        "28" : [ 0, "This", 4, 8, "Muxn", 0 ],
        "38" : [ 0, "This", 6, 10, "Muxn", 0 ],
        "21" : [ 0, "This", 0, 6, "Muxn", 1 ],
        "33" : [ 0, "This", 6, 9, "Muxn", 1 ],
        "9" : [ 0, "This", 0, 3, "Muxn", 1 ],
        "53" : [ 0, "This", 1, 12, "Muxn", 3 ],
        "13" : [ 0, "This", 0, 4, "Muxn", 1 ],
        "41" : [ 0, "This", 2, 10, "Muxn", 3 ],
        "2" : [ 0, "This", 3, 1, "Muxn", 2 ],
        "32" : [ 0, "This", 5, 9, "Muxn", 0 ],
        "34" : [ 0, "This", 1, 9, "Muxn", 2 ],
        "45" : [ 0, "This", 7, 11, "Muxn", 1 ],
        "17" : [ 0, "This", 0, 5, "Muxn", 1 ],
        "22" : [ 0, "This", 1, 6, "Muxn", 2 ],
        "44" : [ 0, "This", 4, 11, "Muxn", 0 ],
        "27" : [ 7, "Muxn", 0, 0, "This", 10 ],
        "12" : [ 0, "This", 6, 4, "Muxn", 0 ],
        "54" : [ 0, "This", 2, 12, "Muxn", 4 ],
        "49" : [ 11, "Muxn", 0, 0, "This", 2 ],
        "7" : [ 2, "Muxn", 0, 0, "This", 5 ],
        "39" : [ 0, "This", 7, 10, "Muxn", 1 ],
        "3" : [ 1, "Muxn", 0, 0, "This", 4 ],
        "35" : [ 0, "This", 2, 9, "Muxn", 3 ],
        "48" : [ 0, "This", 3, 11, "Muxn", 4 ],
        "18" : [ 0, "This", 1, 5, "Muxn", 2 ],
        "50" : [ 0, "This", 4, 12, "Muxn", 0 ],
        "16" : [ 0, "This", 7, 5, "Muxn", 0 ],
        "31" : [ 8, "Muxn", 0, 0, "This", 11 ],
        "11" : [ 3, "Muxn", 0, 0, "This", 6 ],
        "43" : [ 10, "Muxn", 0, 0, "This", 1 ],
        "40" : [ 0, "This", 0, 10, "Muxn", 2 ],
        "26" : [ 0, "This", 2, 7, "Muxn", 2 ],
        "55" : [ 12, "Muxn", 0, 0, "This", 3 ],
        "23" : [ 6, "Muxn", 0, 0, "This", 9 ],
        "8" : [ 0, "This", 4, 3, "Muxn", 0 ],
        "36" : [ 0, "This", 3, 9, "Muxn", 4 ],
        "30" : [ 0, "This", 2, 8, "Muxn", 2 ],
        "51" : [ 0, "This", 5, 12, "Muxn", 1 ],
        "19" : [ 5, "Muxn", 0, 0, "This", 8 ],
        "4" : [ 0, "This", 7, 2, "Muxn", 0 ],
        "47" : [ 0, "This", 1, 11, "Muxn", 3 ],
        "15" : [ 4, "Muxn", 0, 0, "This", 7 ]
      },
      "cfg_blk_index" : 26,
      "num_iopin_list" : {
        "opin_ne" : 1,
        "opin_nw" : 1,
        "opin_sw" : 1,
        "opin_se" : 1,
        "ipin_ne" : 2,
        "ipin_nw" : 2,
        "ipin_sw" : 2,
        "ipin_se" : 2
      }
    },
    "id" : 8
  }, {
    "type" : "GIB",
    "attributes" : {
      "pin_2_track_connection" : {
        "connect_2_side2" : true,
        "connect_2_side4" : false,
        "connect_2_side1" : false,
        "connect_2_side3" : true
      },
      "cfg_data_width" : 32,
      "num_output" : 10,
      "max_II" : 1,
      "cfg_addr_width" : 14,
      "data_width" : 32,
      "y" : 9,
      "num_track" : 1,
      "sub_modules" : [ {
        "id" : 1,
        "type" : "Muxn"
      } ],
      "cfg_blk_offset" : 2,
      "x" : 4,
      "pin_2_pin_connection" : {
        "connect_2_side2" : false,
        "connect_2_side1" : true,
        "connect_2_side3" : true
      },
      "configuration" : {
        "8" : [ "Muxn", 17, 15 ],
        "2" : [ "Muxn", 3, 2 ],
        "5" : [ "Muxn", 9, 8 ],
        "4" : [ "Muxn", 7, 6 ],
        "7" : [ "Muxn", 14, 12 ],
        "10" : [ "Muxn", 23, 21 ],
        "1" : [ "Muxn", 1, 0 ],
        "9" : [ "Muxn", 20, 18 ],
        "3" : [ "Muxn", 5, 4 ],
        "6" : [ "Muxn", 11, 10 ],
        "0" : [ "This", 23, 0 ]
      },
      "instances" : [ {
        "id" : 0,
        "type" : "This",
        "module_id" : 0
      }, {
        "id" : 1,
        "type" : "Muxn",
        "module_id" : 1
      }, {
        "id" : 2,
        "type" : "Muxn",
        "module_id" : 1
      }, {
        "id" : 3,
        "type" : "Muxn",
        "module_id" : 1
      }, {
        "id" : 4,
        "type" : "Muxn",
        "module_id" : 1
      }, {
        "id" : 5,
        "type" : "Muxn",
        "module_id" : 1
      }, {
        "id" : 6,
        "type" : "Muxn",
        "module_id" : 1
      }, {
        "id" : 7,
        "type" : "Muxn",
        "module_id" : 1
      }, {
        "id" : 8,
        "type" : "Muxn",
        "module_id" : 1
      }, {
        "id" : 9,
        "type" : "Muxn",
        "module_id" : 1
      }, {
        "id" : 10,
        "type" : "Muxn",
        "module_id" : 1
      } ],
      "connect_flexibility" : {
        "num_perside_ipin_per_opin" : 1,
        "num_perside_otrack_per_opin" : 1,
        "num_perside_itrack_per_ipin" : 1
      },
      "num_input" : 8,
      "track_reged" : true,
      "connections" : {
        "0" : [ 0, "This", 5, 1, "Muxn", 0 ],
        "5" : [ 0, "This", 2, 2, "Muxn", 1 ],
        "10" : [ 0, "This", 0, 3, "Muxn", 2 ],
        "42" : [ 0, "This", 3, 9, "Muxn", 4 ],
        "24" : [ 0, "This", 2, 6, "Muxn", 2 ],
        "37" : [ 8, "Muxn", 0, 0, "This", 1 ],
        "25" : [ 6, "Muxn", 0, 0, "This", 9 ],
        "14" : [ 0, "This", 7, 4, "Muxn", 1 ],
        "20" : [ 0, "This", 2, 5, "Muxn", 2 ],
        "46" : [ 0, "This", 0, 10, "Muxn", 2 ],
        "29" : [ 0, "This", 2, 7, "Muxn", 3 ],
        "1" : [ 0, "This", 2, 1, "Muxn", 1 ],
        "6" : [ 0, "This", 3, 2, "Muxn", 2 ],
        "28" : [ 0, "This", 1, 7, "Muxn", 2 ],
        "38" : [ 0, "This", 4, 9, "Muxn", 0 ],
        "21" : [ 5, "Muxn", 0, 0, "This", 8 ],
        "33" : [ 0, "This", 7, 8, "Muxn", 1 ],
        "9" : [ 0, "This", 6, 3, "Muxn", 1 ],
        "13" : [ 0, "This", 5, 4, "Muxn", 0 ],
        "41" : [ 0, "This", 1, 9, "Muxn", 3 ],
        "2" : [ 0, "This", 3, 1, "Muxn", 2 ],
        "32" : [ 0, "This", 6, 8, "Muxn", 0 ],
        "34" : [ 0, "This", 0, 8, "Muxn", 2 ],
        "45" : [ 0, "This", 5, 10, "Muxn", 1 ],
        "17" : [ 4, "Muxn", 0, 0, "This", 7 ],
        "22" : [ 0, "This", 4, 6, "Muxn", 0 ],
        "44" : [ 0, "This", 4, 10, "Muxn", 0 ],
        "27" : [ 0, "This", 6, 7, "Muxn", 1 ],
        "12" : [ 3, "Muxn", 0, 0, "This", 6 ],
        "49" : [ 10, "Muxn", 0, 0, "This", 3 ],
        "7" : [ 2, "Muxn", 0, 0, "This", 5 ],
        "39" : [ 0, "This", 7, 9, "Muxn", 1 ],
        "3" : [ 1, "Muxn", 0, 0, "This", 4 ],
        "35" : [ 0, "This", 2, 8, "Muxn", 3 ],
        "48" : [ 0, "This", 2, 10, "Muxn", 4 ],
        "18" : [ 0, "This", 6, 5, "Muxn", 0 ],
        "16" : [ 0, "This", 1, 4, "Muxn", 3 ],
        "31" : [ 7, "Muxn", 0, 0, "This", 0 ],
        "11" : [ 0, "This", 3, 3, "Muxn", 3 ],
        "43" : [ 9, "Muxn", 0, 0, "This", 2 ],
        "40" : [ 0, "This", 0, 9, "Muxn", 2 ],
        "26" : [ 0, "This", 5, 7, "Muxn", 0 ],
        "23" : [ 0, "This", 1, 6, "Muxn", 1 ],
        "8" : [ 0, "This", 4, 3, "Muxn", 0 ],
        "36" : [ 0, "This", 3, 8, "Muxn", 4 ],
        "30" : [ 0, "This", 3, 7, "Muxn", 4 ],
        "19" : [ 0, "This", 1, 5, "Muxn", 1 ],
        "4" : [ 0, "This", 7, 2, "Muxn", 0 ],
        "47" : [ 0, "This", 1, 10, "Muxn", 3 ],
        "15" : [ 0, "This", 0, 4, "Muxn", 2 ]
      },
      "cfg_blk_index" : 29,
      "num_iopin_list" : {
        "opin_ne" : 1,
        "opin_nw" : 1,
        "opin_sw" : 1,
        "opin_se" : 1,
        "ipin_ne" : 1,
        "ipin_nw" : 2,
        "ipin_sw" : 2,
        "ipin_se" : 1
      }
    },
    "id" : 9
  }, {
    "type" : "GIB",
    "attributes" : {
      "pin_2_track_connection" : {
        "connect_2_side2" : true,
        "connect_2_side4" : false,
        "connect_2_side1" : false,
        "connect_2_side3" : true
      },
      "cfg_data_width" : 32,
      "num_output" : 8,
      "max_II" : 1,
      "cfg_addr_width" : 14,
      "data_width" : 32,
      "y" : 1,
      "num_track" : 1,
      "sub_modules" : [ {
        "id" : 1,
        "type" : "Muxn"
      } ],
      "cfg_blk_offset" : 2,
      "x" : 20,
      "pin_2_pin_connection" : {
        "connect_2_side2" : false,
        "connect_2_side1" : true,
        "connect_2_side3" : true
      },
      "configuration" : {
        "8" : [ "Muxn", 17, 15 ],
        "2" : [ "Muxn", 3, 2 ],
        "5" : [ "Muxn", 10, 8 ],
        "4" : [ "Muxn", 7, 6 ],
        "7" : [ "Muxn", 14, 13 ],
        "1" : [ "Muxn", 1, 0 ],
        "3" : [ "Muxn", 5, 4 ],
        "6" : [ "Muxn", 12, 11 ],
        "0" : [ "This", 17, 0 ]
      },
      "instances" : [ {
        "id" : 0,
        "type" : "This",
        "module_id" : 0
      }, {
        "id" : 1,
        "type" : "Muxn",
        "module_id" : 1
      }, {
        "id" : 2,
        "type" : "Muxn",
        "module_id" : 1
      }, {
        "id" : 3,
        "type" : "Muxn",
        "module_id" : 1
      }, {
        "id" : 4,
        "type" : "Muxn",
        "module_id" : 1
      }, {
        "id" : 5,
        "type" : "Muxn",
        "module_id" : 1
      }, {
        "id" : 6,
        "type" : "Muxn",
        "module_id" : 1
      }, {
        "id" : 7,
        "type" : "Muxn",
        "module_id" : 1
      }, {
        "id" : 8,
        "type" : "Muxn",
        "module_id" : 1
      } ],
      "connect_flexibility" : {
        "num_perside_ipin_per_opin" : 1,
        "num_perside_otrack_per_opin" : 1,
        "num_perside_itrack_per_ipin" : 1
      },
      "num_input" : 7,
      "track_reged" : true,
      "connections" : {
        "0" : [ 0, "This", 5, 1, "Muxn", 0 ],
        "5" : [ 0, "This", 0, 2, "Muxn", 1 ],
        "10" : [ 0, "This", 3, 3, "Muxn", 2 ],
        "24" : [ 0, "This", 2, 6, "Muxn", 2 ],
        "37" : [ 8, "Muxn", 0, 0, "This", 3 ],
        "25" : [ 0, "This", 3, 6, "Muxn", 3 ],
        "14" : [ 0, "This", 1, 4, "Muxn", 2 ],
        "20" : [ 0, "This", 3, 5, "Muxn", 4 ],
        "29" : [ 0, "This", 1, 7, "Muxn", 2 ],
        "1" : [ 0, "This", 2, 1, "Muxn", 1 ],
        "6" : [ 0, "This", 3, 2, "Muxn", 2 ],
        "28" : [ 0, "This", 0, 7, "Muxn", 1 ],
        "21" : [ 5, "Muxn", 0, 0, "This", 0 ],
        "33" : [ 0, "This", 5, 8, "Muxn", 1 ],
        "9" : [ 0, "This", 0, 3, "Muxn", 1 ],
        "13" : [ 0, "This", 0, 4, "Muxn", 1 ],
        "2" : [ 0, "This", 3, 1, "Muxn", 2 ],
        "32" : [ 0, "This", 4, 8, "Muxn", 0 ],
        "34" : [ 0, "This", 0, 8, "Muxn", 2 ],
        "17" : [ 0, "This", 6, 5, "Muxn", 1 ],
        "22" : [ 0, "This", 6, 6, "Muxn", 0 ],
        "27" : [ 0, "This", 4, 7, "Muxn", 0 ],
        "12" : [ 0, "This", 5, 4, "Muxn", 0 ],
        "7" : [ 2, "Muxn", 0, 0, "This", 5 ],
        "3" : [ 1, "Muxn", 0, 0, "This", 4 ],
        "35" : [ 0, "This", 1, 8, "Muxn", 3 ],
        "18" : [ 0, "This", 1, 5, "Muxn", 2 ],
        "16" : [ 0, "This", 5, 5, "Muxn", 0 ],
        "31" : [ 7, "Muxn", 0, 0, "This", 2 ],
        "11" : [ 3, "Muxn", 0, 0, "This", 6 ],
        "26" : [ 6, "Muxn", 0, 0, "This", 1 ],
        "23" : [ 0, "This", 0, 6, "Muxn", 1 ],
        "8" : [ 0, "This", 6, 3, "Muxn", 0 ],
        "36" : [ 0, "This", 2, 8, "Muxn", 4 ],
        "30" : [ 0, "This", 3, 7, "Muxn", 3 ],
        "19" : [ 0, "This", 2, 5, "Muxn", 3 ],
        "4" : [ 0, "This", 4, 2, "Muxn", 0 ],
        "15" : [ 4, "Muxn", 0, 0, "This", 7 ]
      },
      "cfg_blk_index" : 121,
      "num_iopin_list" : {
        "opin_ne" : 1,
        "opin_nw" : 1,
        "opin_sw" : 0,
        "opin_se" : 1,
        "ipin_ne" : 2,
        "ipin_nw" : 1,
        "ipin_sw" : 0,
        "ipin_se" : 1
      }
    },
    "id" : 10
  }, {
    "type" : "GIB",
    "attributes" : {
      "pin_2_track_connection" : {
        "connect_2_side2" : true,
        "connect_2_side4" : false,
        "connect_2_side1" : false,
        "connect_2_side3" : true
      },
      "cfg_data_width" : 32,
      "num_output" : 10,
      "max_II" : 1,
      "cfg_addr_width" : 14,
      "data_width" : 32,
      "y" : 3,
      "num_track" : 1,
      "sub_modules" : [ {
        "id" : 1,
        "type" : "Muxn"
      } ],
      "cfg_blk_offset" : 2,
      "x" : 20,
      "pin_2_pin_connection" : {
        "connect_2_side2" : false,
        "connect_2_side1" : true,
        "connect_2_side3" : true
      },
      "configuration" : {
        "8" : [ "Muxn", 17, 15 ],
        "2" : [ "Muxn", 3, 2 ],
        "5" : [ "Muxn", 9, 8 ],
        "4" : [ "Muxn", 7, 6 ],
        "7" : [ "Muxn", 14, 12 ],
        "10" : [ "Muxn", 23, 21 ],
        "1" : [ "Muxn", 1, 0 ],
        "9" : [ "Muxn", 20, 18 ],
        "3" : [ "Muxn", 5, 4 ],
        "6" : [ "Muxn", 11, 10 ],
        "0" : [ "This", 23, 0 ]
      },
      "instances" : [ {
        "id" : 0,
        "type" : "This",
        "module_id" : 0
      }, {
        "id" : 1,
        "type" : "Muxn",
        "module_id" : 1
      }, {
        "id" : 2,
        "type" : "Muxn",
        "module_id" : 1
      }, {
        "id" : 3,
        "type" : "Muxn",
        "module_id" : 1
      }, {
        "id" : 4,
        "type" : "Muxn",
        "module_id" : 1
      }, {
        "id" : 5,
        "type" : "Muxn",
        "module_id" : 1
      }, {
        "id" : 6,
        "type" : "Muxn",
        "module_id" : 1
      }, {
        "id" : 7,
        "type" : "Muxn",
        "module_id" : 1
      }, {
        "id" : 8,
        "type" : "Muxn",
        "module_id" : 1
      }, {
        "id" : 9,
        "type" : "Muxn",
        "module_id" : 1
      }, {
        "id" : 10,
        "type" : "Muxn",
        "module_id" : 1
      } ],
      "connect_flexibility" : {
        "num_perside_ipin_per_opin" : 1,
        "num_perside_otrack_per_opin" : 1,
        "num_perside_itrack_per_ipin" : 1
      },
      "num_input" : 8,
      "track_reged" : false,
      "connections" : {
        "0" : [ 0, "This", 5, 1, "Muxn", 0 ],
        "5" : [ 0, "This", 2, 2, "Muxn", 1 ],
        "10" : [ 0, "This", 3, 3, "Muxn", 2 ],
        "42" : [ 0, "This", 3, 9, "Muxn", 4 ],
        "24" : [ 0, "This", 2, 6, "Muxn", 3 ],
        "37" : [ 8, "Muxn", 0, 0, "This", 1 ],
        "25" : [ 6, "Muxn", 0, 0, "This", 9 ],
        "14" : [ 0, "This", 3, 4, "Muxn", 2 ],
        "20" : [ 5, "Muxn", 0, 0, "This", 8 ],
        "46" : [ 0, "This", 0, 10, "Muxn", 2 ],
        "29" : [ 0, "This", 2, 7, "Muxn", 3 ],
        "1" : [ 0, "This", 2, 1, "Muxn", 1 ],
        "6" : [ 0, "This", 3, 2, "Muxn", 2 ],
        "28" : [ 0, "This", 1, 7, "Muxn", 2 ],
        "38" : [ 0, "This", 4, 9, "Muxn", 0 ],
        "21" : [ 0, "This", 4, 6, "Muxn", 0 ],
        "33" : [ 0, "This", 7, 8, "Muxn", 1 ],
        "9" : [ 0, "This", 0, 3, "Muxn", 1 ],
        "13" : [ 0, "This", 0, 4, "Muxn", 1 ],
        "41" : [ 0, "This", 1, 9, "Muxn", 3 ],
        "2" : [ 0, "This", 3, 1, "Muxn", 2 ],
        "32" : [ 0, "This", 6, 8, "Muxn", 0 ],
        "34" : [ 0, "This", 0, 8, "Muxn", 2 ],
        "45" : [ 0, "This", 5, 10, "Muxn", 1 ],
        "17" : [ 0, "This", 7, 5, "Muxn", 1 ],
        "22" : [ 0, "This", 6, 6, "Muxn", 1 ],
        "44" : [ 0, "This", 4, 10, "Muxn", 0 ],
        "27" : [ 0, "This", 6, 7, "Muxn", 1 ],
        "12" : [ 0, "This", 6, 4, "Muxn", 0 ],
        "49" : [ 10, "Muxn", 0, 0, "This", 3 ],
        "7" : [ 2, "Muxn", 0, 0, "This", 5 ],
        "39" : [ 0, "This", 7, 9, "Muxn", 1 ],
        "3" : [ 1, "Muxn", 0, 0, "This", 4 ],
        "35" : [ 0, "This", 2, 8, "Muxn", 3 ],
        "48" : [ 0, "This", 2, 10, "Muxn", 4 ],
        "18" : [ 0, "This", 0, 5, "Muxn", 2 ],
        "16" : [ 0, "This", 5, 5, "Muxn", 0 ],
        "31" : [ 7, "Muxn", 0, 0, "This", 0 ],
        "11" : [ 3, "Muxn", 0, 0, "This", 6 ],
        "43" : [ 9, "Muxn", 0, 0, "This", 2 ],
        "40" : [ 0, "This", 0, 9, "Muxn", 2 ],
        "26" : [ 0, "This", 5, 7, "Muxn", 0 ],
        "23" : [ 0, "This", 1, 6, "Muxn", 2 ],
        "8" : [ 0, "This", 4, 3, "Muxn", 0 ],
        "36" : [ 0, "This", 3, 8, "Muxn", 4 ],
        "30" : [ 0, "This", 3, 7, "Muxn", 4 ],
        "19" : [ 0, "This", 1, 5, "Muxn", 3 ],
        "4" : [ 0, "This", 7, 2, "Muxn", 0 ],
        "47" : [ 0, "This", 1, 10, "Muxn", 3 ],
        "15" : [ 4, "Muxn", 0, 0, "This", 7 ]
      },
      "cfg_blk_index" : 122,
      "num_iopin_list" : {
        "opin_ne" : 1,
        "opin_nw" : 1,
        "opin_sw" : 1,
        "opin_se" : 1,
        "ipin_ne" : 2,
        "ipin_nw" : 2,
        "ipin_sw" : 1,
        "ipin_se" : 1
      }
    },
    "id" : 11
  }, {
    "type" : "GIB",
    "attributes" : {
      "pin_2_track_connection" : {
        "connect_2_side2" : true,
        "connect_2_side4" : false,
        "connect_2_side1" : false,
        "connect_2_side3" : true
      },
      "cfg_data_width" : 32,
      "num_output" : 8,
      "max_II" : 1,
      "cfg_addr_width" : 14,
      "data_width" : 32,
      "y" : 9,
      "num_track" : 1,
      "sub_modules" : [ {
        "id" : 1,
        "type" : "Muxn"
      } ],
      "cfg_blk_offset" : 2,
      "x" : 20,
      "pin_2_pin_connection" : {
        "connect_2_side2" : false,
        "connect_2_side1" : true,
        "connect_2_side3" : true
      },
      "configuration" : {
        "8" : [ "Muxn", 17, 15 ],
        "2" : [ "Muxn", 3, 2 ],
        "5" : [ "Muxn", 9, 8 ],
        "4" : [ "Muxn", 7, 6 ],
        "7" : [ "Muxn", 14, 12 ],
        "1" : [ "Muxn", 1, 0 ],
        "3" : [ "Muxn", 5, 4 ],
        "6" : [ "Muxn", 11, 10 ],
        "0" : [ "This", 17, 0 ]
      },
      "instances" : [ {
        "id" : 0,
        "type" : "This",
        "module_id" : 0
      }, {
        "id" : 1,
        "type" : "Muxn",
        "module_id" : 1
      }, {
        "id" : 2,
        "type" : "Muxn",
        "module_id" : 1
      }, {
        "id" : 3,
        "type" : "Muxn",
        "module_id" : 1
      }, {
        "id" : 4,
        "type" : "Muxn",
        "module_id" : 1
      }, {
        "id" : 5,
        "type" : "Muxn",
        "module_id" : 1
      }, {
        "id" : 6,
        "type" : "Muxn",
        "module_id" : 1
      }, {
        "id" : 7,
        "type" : "Muxn",
        "module_id" : 1
      }, {
        "id" : 8,
        "type" : "Muxn",
        "module_id" : 1
      } ],
      "connect_flexibility" : {
        "num_perside_ipin_per_opin" : 1,
        "num_perside_otrack_per_opin" : 1,
        "num_perside_itrack_per_ipin" : 1
      },
      "num_input" : 7,
      "track_reged" : true,
      "connections" : {
        "0" : [ 0, "This", 5, 1, "Muxn", 0 ],
        "5" : [ 0, "This", 2, 2, "Muxn", 1 ],
        "10" : [ 0, "This", 3, 3, "Muxn", 2 ],
        "24" : [ 0, "This", 3, 6, "Muxn", 3 ],
        "37" : [ 8, "Muxn", 0, 0, "This", 3 ],
        "25" : [ 6, "Muxn", 0, 0, "This", 1 ],
        "14" : [ 0, "This", 2, 4, "Muxn", 2 ],
        "20" : [ 5, "Muxn", 0, 0, "This", 0 ],
        "29" : [ 0, "This", 1, 7, "Muxn", 3 ],
        "1" : [ 0, "This", 2, 1, "Muxn", 1 ],
        "6" : [ 0, "This", 3, 2, "Muxn", 2 ],
        "28" : [ 0, "This", 0, 7, "Muxn", 2 ],
        "21" : [ 0, "This", 6, 6, "Muxn", 0 ],
        "33" : [ 0, "This", 5, 8, "Muxn", 1 ],
        "9" : [ 0, "This", 0, 3, "Muxn", 1 ],
        "13" : [ 0, "This", 1, 4, "Muxn", 1 ],
        "2" : [ 0, "This", 3, 1, "Muxn", 2 ],
        "32" : [ 0, "This", 4, 8, "Muxn", 0 ],
        "34" : [ 0, "This", 0, 8, "Muxn", 2 ],
        "17" : [ 0, "This", 1, 5, "Muxn", 1 ],
        "22" : [ 0, "This", 0, 6, "Muxn", 1 ],
        "27" : [ 0, "This", 6, 7, "Muxn", 1 ],
        "12" : [ 0, "This", 4, 4, "Muxn", 0 ],
        "7" : [ 2, "Muxn", 0, 0, "This", 5 ],
        "3" : [ 1, "Muxn", 0, 0, "This", 4 ],
        "35" : [ 0, "This", 1, 8, "Muxn", 3 ],
        "18" : [ 0, "This", 2, 5, "Muxn", 2 ],
        "16" : [ 0, "This", 5, 5, "Muxn", 0 ],
        "31" : [ 7, "Muxn", 0, 0, "This", 2 ],
        "11" : [ 3, "Muxn", 0, 0, "This", 6 ],
        "26" : [ 0, "This", 4, 7, "Muxn", 0 ],
        "23" : [ 0, "This", 2, 6, "Muxn", 2 ],
        "8" : [ 0, "This", 4, 3, "Muxn", 0 ],
        "36" : [ 0, "This", 2, 8, "Muxn", 4 ],
        "30" : [ 0, "This", 3, 7, "Muxn", 4 ],
        "19" : [ 0, "This", 3, 5, "Muxn", 3 ],
        "4" : [ 0, "This", 6, 2, "Muxn", 0 ],
        "15" : [ 4, "Muxn", 0, 0, "This", 7 ]
      },
      "cfg_blk_index" : 125,
      "num_iopin_list" : {
        "opin_ne" : 1,
        "opin_nw" : 1,
        "opin_sw" : 1,
        "opin_se" : 0,
        "ipin_ne" : 1,
        "ipin_nw" : 2,
        "ipin_sw" : 1,
        "ipin_se" : 0
      }
    },
    "id" : 12
  }, {
    "type" : "IB",
    "attributes" : {
      "cfg_data_width" : 32,
      "max_II" : 1,
      "num_output" : 1,
      "cfg_addr_width" : 14,
      "data_width" : 32,
      "y" : 8,
      "cfg_blk_offset" : 2,
      "x" : 21,
      "instances" : [ {
        "id" : 0,
        "type" : "This",
        "module_id" : 0
      } ],
      "num_input" : 1,
      "connections" : {
        "0" : [ 0, "This", 0, 0, "This", 0 ]
      },
      "cfg_blk_index" : 130
    },
    "id" : 1
  }, {
    "type" : "LSU",
    "attributes" : {
      "operations" : [ "LOAD", "STORE" ],
      "cfg_data_width" : 32,
      "num_operands" : 2,
      "num_mem_perin" : 1,
      "num_output" : 1,
      "num_mem_out" : 1,
      "max_II" : 1,
      "cfg_addr_width" : 14,
      "memory_depth_percycle" : 64,
      "data_width" : 32,
      "y" : 10,
      "sub_modules" : [ {
        "id" : 1,
        "type" : "SRAM"
      }, {
        "id" : 2,
        "type" : "Const"
      }, {
        "id" : 3,
        "type" : "DelayPipe"
      }, {
        "id" : 4,
        "type" : "Muxn"
      } ],
      "cfg_blk_offset" : 2,
      "x" : 19,
      "configuration" : {
        "2" : [ "Const", 31, 0 ],
        "5" : [ "Muxn", 32, 32 ],
        "4" : [ "DelayPipe", 39, 37 ],
        "1" : [ "SRAM", 40, 40 ],
        "3" : [ "DelayPipe", 36, 34 ],
        "6" : [ "Muxn", 33, 33 ],
        "0" : [ "This", 40, 0 ]
      },
      "instances" : [ {
        "id" : 0,
        "type" : "This",
        "module_id" : 0
      }, {
        "id" : 3,
        "type" : "DelayPipe",
        "module_id" : 3
      }, {
        "id" : 4,
        "type" : "DelayPipe",
        "module_id" : 3
      }, {
        "id" : 5,
        "type" : "Muxn",
        "module_id" : 4
      }, {
        "id" : 6,
        "type" : "Muxn",
        "module_id" : 4
      }, {
        "id" : 1,
        "type" : "SRAM",
        "module_id" : 1
      }, {
        "id" : 2,
        "type" : "Const",
        "module_id" : 2
      } ],
      "num_input" : 2,
      "connections" : {
        "0" : [ 0, "This", 0, 5, "Muxn", 0 ],
        "5" : [ 2, "Const", 0, 6, "Muxn", 1 ],
        "1" : [ 0, "This", 1, 6, "Muxn", 0 ],
        "6" : [ 6, "Muxn", 0, 4, "DelayPipe", 0 ],
        "2" : [ 2, "Const", 0, 5, "Muxn", 1 ],
        "7" : [ 4, "DelayPipe", 0, 1, "SRAM", 1 ],
        "3" : [ 5, "Muxn", 0, 3, "DelayPipe", 0 ],
        "8" : [ 1, "SRAM", 0, 0, "This", 0 ],
        "4" : [ 3, "DelayPipe", 0, 1, "SRAM", 0 ]
      },
      "cfg_blk_index" : 120,
      "max_delay" : 4
    },
    "id" : 13
  }, {
    "type" : "GPE",
    "attributes" : {
      "num_rf_reg" : 1,
      "operations" : [ "PASS", "ADD", "SUB", "MUL", "AND", "OR", "XOR" ],
      "cfg_data_width" : 32,
      "num_operands" : 2,
      "num_output" : 1,
      "max_II" : 1,
      "cfg_addr_width" : 14,
      "y" : 8,
      "data_width" : 32,
      "num_input_per_operand" : [ 4, 4 ],
      "sub_modules" : [ {
        "id" : 3,
        "type" : "RF"
      }, {
        "id" : 4,
        "type" : "DelayPipe"
      }, {
        "id" : 5,
        "type" : "Muxn"
      }, {
        "id" : 2,
        "type" : "ALU"
      }, {
        "id" : 1,
        "type" : "Const"
      } ],
      "x" : 19,
      "cfg_blk_offset" : 2,
      "configuration" : {
        "2" : [ "ALU", 36, 32 ],
        "5" : [ "DelayPipe", 42, 40 ],
        "4" : [ "DelayPipe", 39, 37 ],
        "7" : [ "Muxn", 48, 46 ],
        "1" : [ "Const", 31, 0 ],
        "6" : [ "Muxn", 45, 43 ],
        "0" : [ "This", 48, 0 ]
      },
      "instances" : [ {
        "id" : 3,
        "type" : "RF",
        "module_id" : 3
      }, {
        "id" : 0,
        "type" : "This",
        "module_id" : 0
      }, {
        "id" : 4,
        "type" : "DelayPipe",
        "module_id" : 4
      }, {
        "id" : 5,
        "type" : "DelayPipe",
        "module_id" : 4
      }, {
        "id" : 6,
        "type" : "Muxn",
        "module_id" : 5
      }, {
        "id" : 7,
        "type" : "Muxn",
        "module_id" : 5
      }, {
        "id" : 2,
        "type" : "ALU",
        "module_id" : 2
      }, {
        "id" : 1,
        "type" : "Const",
        "module_id" : 1
      } ],
      "num_input" : 8,
      "connections" : {
        "0" : [ 2, "ALU", 0, 3, "RF", 0 ],
        "5" : [ 0, "This", 3, 6, "Muxn", 3 ],
        "10" : [ 0, "This", 4, 7, "Muxn", 0 ],
        "14" : [ 1, "Const", 0, 7, "Muxn", 4 ],
        "1" : [ 3, "RF", 0, 0, "This", 0 ],
        "6" : [ 1, "Const", 0, 6, "Muxn", 4 ],
        "9" : [ 4, "DelayPipe", 0, 2, "ALU", 0 ],
        "13" : [ 0, "This", 7, 7, "Muxn", 3 ],
        "2" : [ 0, "This", 0, 6, "Muxn", 0 ],
        "17" : [ 5, "DelayPipe", 0, 2, "ALU", 1 ],
        "12" : [ 0, "This", 6, 7, "Muxn", 2 ],
        "7" : [ 3, "RF", 1, 6, "Muxn", 5 ],
        "3" : [ 0, "This", 1, 6, "Muxn", 1 ],
        "16" : [ 7, "Muxn", 0, 5, "DelayPipe", 0 ],
        "11" : [ 0, "This", 5, 7, "Muxn", 1 ],
        "8" : [ 6, "Muxn", 0, 4, "DelayPipe", 0 ],
        "4" : [ 0, "This", 2, 6, "Muxn", 2 ],
        "15" : [ 3, "RF", 1, 7, "Muxn", 5 ]
      },
      "max_delay" : 4,
      "cfg_blk_index" : 119
    },
    "id" : 3
  }, {
    "type" : "OB",
    "attributes" : {
      "cfg_data_width" : 32,
      "num_output" : 1,
      "max_II" : 1,
      "cfg_addr_width" : 14,
      "y" : 8,
      "data_width" : 32,
      "x" : 22,
      "cfg_blk_offset" : 2,
      "sub_modules" : [ {
        "id" : 1,
        "type" : "Muxn"
      } ],
      "configuration" : {
        "1" : [ "Muxn", 0, 0 ],
        "0" : [ "This", 0, 0 ]
      },
      "instances" : [ {
        "id" : 0,
        "type" : "This",
        "module_id" : 0
      }, {
        "id" : 1,
        "type" : "Muxn",
        "module_id" : 1
      } ],
      "num_input" : 2,
      "cfg_blk_index" : 136,
      "connections" : {
        "0" : [ 0, "This", 0, 1, "Muxn", 0 ],
        "1" : [ 0, "This", 1, 1, "Muxn", 1 ],
        "2" : [ 1, "Muxn", 0, 0, "This", 0 ]
      }
    },
    "id" : 2
  } ],
  "pin_2_pin_connection" : {
    "connect_2_side2" : false,
    "connect_2_side1" : true,
    "connect_2_side3" : true
  },
  "cfg_blk_offset" : 2,
  "connect_flexibility" : {
    "num_perside_ipin_per_opin" : 1,
    "num_perside_otrack_per_opin" : 1,
    "num_perside_itrack_per_ipin" : 1
  },
  "instances" : [ {
    "module_id" : 4,
    "type" : "GIB",
    "y" : 1,
    "x" : 2,
    "track_reged" : false,
    "cfg_blk_index" : 13,
    "id" : 13
  }, {
    "module_id" : 5,
    "type" : "GIB",
    "y" : 3,
    "x" : 2,
    "track_reged" : true,
    "cfg_blk_index" : 14,
    "id" : 14
  }, {
    "module_id" : 5,
    "type" : "GIB",
    "y" : 5,
    "x" : 2,
    "track_reged" : false,
    "cfg_blk_index" : 15,
    "id" : 15
  }, {
    "module_id" : 5,
    "type" : "GIB",
    "y" : 7,
    "x" : 2,
    "track_reged" : true,
    "cfg_blk_index" : 16,
    "id" : 16
  }, {
    "module_id" : 6,
    "type" : "GIB",
    "y" : 9,
    "x" : 2,
    "track_reged" : false,
    "cfg_blk_index" : 17,
    "id" : 17
  }, {
    "module_id" : 7,
    "type" : "GIB",
    "y" : 1,
    "x" : 4,
    "track_reged" : true,
    "cfg_blk_index" : 25,
    "id" : 25
  }, {
    "module_id" : 8,
    "type" : "GIB",
    "y" : 3,
    "x" : 4,
    "track_reged" : false,
    "cfg_blk_index" : 26,
    "id" : 26
  }, {
    "module_id" : 8,
    "type" : "GIB",
    "y" : 5,
    "x" : 4,
    "track_reged" : true,
    "cfg_blk_index" : 27,
    "id" : 27
  }, {
    "module_id" : 8,
    "type" : "GIB",
    "y" : 7,
    "x" : 4,
    "track_reged" : false,
    "cfg_blk_index" : 28,
    "id" : 28
  }, {
    "module_id" : 9,
    "type" : "GIB",
    "y" : 9,
    "x" : 4,
    "track_reged" : true,
    "cfg_blk_index" : 29,
    "id" : 29
  }, {
    "module_id" : 7,
    "type" : "GIB",
    "y" : 1,
    "x" : 6,
    "track_reged" : false,
    "cfg_blk_index" : 37,
    "id" : 37
  }, {
    "module_id" : 8,
    "type" : "GIB",
    "y" : 3,
    "x" : 6,
    "track_reged" : true,
    "cfg_blk_index" : 38,
    "id" : 38
  }, {
    "module_id" : 8,
    "type" : "GIB",
    "y" : 5,
    "x" : 6,
    "track_reged" : false,
    "cfg_blk_index" : 39,
    "id" : 39
  }, {
    "module_id" : 8,
    "type" : "GIB",
    "y" : 7,
    "x" : 6,
    "track_reged" : true,
    "cfg_blk_index" : 40,
    "id" : 40
  }, {
    "module_id" : 9,
    "type" : "GIB",
    "y" : 9,
    "x" : 6,
    "track_reged" : false,
    "cfg_blk_index" : 41,
    "id" : 41
  }, {
    "module_id" : 7,
    "type" : "GIB",
    "y" : 1,
    "x" : 8,
    "track_reged" : true,
    "cfg_blk_index" : 49,
    "id" : 49
  }, {
    "module_id" : 8,
    "type" : "GIB",
    "y" : 3,
    "x" : 8,
    "track_reged" : false,
    "cfg_blk_index" : 50,
    "id" : 50
  }, {
    "module_id" : 8,
    "type" : "GIB",
    "y" : 5,
    "x" : 8,
    "track_reged" : true,
    "cfg_blk_index" : 51,
    "id" : 51
  }, {
    "module_id" : 8,
    "type" : "GIB",
    "y" : 7,
    "x" : 8,
    "track_reged" : false,
    "cfg_blk_index" : 52,
    "id" : 52
  }, {
    "module_id" : 9,
    "type" : "GIB",
    "y" : 9,
    "x" : 8,
    "track_reged" : true,
    "cfg_blk_index" : 53,
    "id" : 53
  }, {
    "module_id" : 7,
    "type" : "GIB",
    "y" : 1,
    "x" : 10,
    "track_reged" : false,
    "cfg_blk_index" : 61,
    "id" : 61
  }, {
    "module_id" : 8,
    "type" : "GIB",
    "y" : 3,
    "x" : 10,
    "track_reged" : true,
    "cfg_blk_index" : 62,
    "id" : 62
  }, {
    "module_id" : 8,
    "type" : "GIB",
    "y" : 5,
    "x" : 10,
    "track_reged" : false,
    "cfg_blk_index" : 63,
    "id" : 63
  }, {
    "module_id" : 8,
    "type" : "GIB",
    "y" : 7,
    "x" : 10,
    "track_reged" : true,
    "cfg_blk_index" : 64,
    "id" : 64
  }, {
    "module_id" : 9,
    "type" : "GIB",
    "y" : 9,
    "x" : 10,
    "track_reged" : false,
    "cfg_blk_index" : 65,
    "id" : 65
  }, {
    "module_id" : 7,
    "type" : "GIB",
    "y" : 1,
    "x" : 12,
    "track_reged" : true,
    "cfg_blk_index" : 73,
    "id" : 73
  }, {
    "module_id" : 8,
    "type" : "GIB",
    "y" : 3,
    "x" : 12,
    "track_reged" : false,
    "cfg_blk_index" : 74,
    "id" : 74
  }, {
    "module_id" : 8,
    "type" : "GIB",
    "y" : 5,
    "x" : 12,
    "track_reged" : true,
    "cfg_blk_index" : 75,
    "id" : 75
  }, {
    "module_id" : 8,
    "type" : "GIB",
    "y" : 7,
    "x" : 12,
    "track_reged" : false,
    "cfg_blk_index" : 76,
    "id" : 76
  }, {
    "module_id" : 9,
    "type" : "GIB",
    "y" : 9,
    "x" : 12,
    "track_reged" : true,
    "cfg_blk_index" : 77,
    "id" : 77
  }, {
    "module_id" : 7,
    "type" : "GIB",
    "y" : 1,
    "x" : 14,
    "track_reged" : false,
    "cfg_blk_index" : 85,
    "id" : 85
  }, {
    "module_id" : 8,
    "type" : "GIB",
    "y" : 3,
    "x" : 14,
    "track_reged" : true,
    "cfg_blk_index" : 86,
    "id" : 86
  }, {
    "module_id" : 8,
    "type" : "GIB",
    "y" : 5,
    "x" : 14,
    "track_reged" : false,
    "cfg_blk_index" : 87,
    "id" : 87
  }, {
    "module_id" : 8,
    "type" : "GIB",
    "y" : 7,
    "x" : 14,
    "track_reged" : true,
    "cfg_blk_index" : 88,
    "id" : 88
  }, {
    "module_id" : 9,
    "type" : "GIB",
    "y" : 9,
    "x" : 14,
    "track_reged" : false,
    "cfg_blk_index" : 89,
    "id" : 89
  }, {
    "module_id" : 7,
    "type" : "GIB",
    "y" : 1,
    "x" : 16,
    "track_reged" : true,
    "cfg_blk_index" : 97,
    "id" : 97
  }, {
    "module_id" : 8,
    "type" : "GIB",
    "y" : 3,
    "x" : 16,
    "track_reged" : false,
    "cfg_blk_index" : 98,
    "id" : 98
  }, {
    "module_id" : 8,
    "type" : "GIB",
    "y" : 5,
    "x" : 16,
    "track_reged" : true,
    "cfg_blk_index" : 99,
    "id" : 99
  }, {
    "module_id" : 8,
    "type" : "GIB",
    "y" : 7,
    "x" : 16,
    "track_reged" : false,
    "cfg_blk_index" : 100,
    "id" : 100
  }, {
    "module_id" : 9,
    "type" : "GIB",
    "y" : 9,
    "x" : 16,
    "track_reged" : true,
    "cfg_blk_index" : 101,
    "id" : 101
  }, {
    "module_id" : 7,
    "type" : "GIB",
    "y" : 1,
    "x" : 18,
    "track_reged" : false,
    "cfg_blk_index" : 109,
    "id" : 109
  }, {
    "module_id" : 8,
    "type" : "GIB",
    "y" : 3,
    "x" : 18,
    "track_reged" : true,
    "cfg_blk_index" : 110,
    "id" : 110
  }, {
    "module_id" : 8,
    "type" : "GIB",
    "y" : 5,
    "x" : 18,
    "track_reged" : false,
    "cfg_blk_index" : 111,
    "id" : 111
  }, {
    "module_id" : 8,
    "type" : "GIB",
    "y" : 7,
    "x" : 18,
    "track_reged" : true,
    "cfg_blk_index" : 112,
    "id" : 112
  }, {
    "module_id" : 9,
    "type" : "GIB",
    "y" : 9,
    "x" : 18,
    "track_reged" : false,
    "cfg_blk_index" : 113,
    "id" : 113
  }, {
    "module_id" : 10,
    "type" : "GIB",
    "y" : 1,
    "x" : 20,
    "track_reged" : true,
    "cfg_blk_index" : 121,
    "id" : 121
  }, {
    "module_id" : 11,
    "type" : "GIB",
    "y" : 3,
    "x" : 20,
    "track_reged" : false,
    "cfg_blk_index" : 122,
    "id" : 122
  }, {
    "module_id" : 11,
    "type" : "GIB",
    "y" : 5,
    "x" : 20,
    "track_reged" : true,
    "cfg_blk_index" : 123,
    "id" : 123
  }, {
    "module_id" : 11,
    "type" : "GIB",
    "y" : 7,
    "x" : 20,
    "track_reged" : false,
    "cfg_blk_index" : 124,
    "id" : 124
  }, {
    "module_id" : 12,
    "type" : "GIB",
    "y" : 9,
    "x" : 20,
    "track_reged" : true,
    "cfg_blk_index" : 125,
    "id" : 125
  }, {
    "module_id" : 1,
    "type" : "IB",
    "y" : 2,
    "x" : 0,
    "cfg_blk_index" : 1,
    "id" : 1
  }, {
    "module_id" : 1,
    "type" : "IB",
    "y" : 4,
    "x" : 0,
    "cfg_blk_index" : 2,
    "id" : 2
  }, {
    "module_id" : 1,
    "type" : "IB",
    "y" : 6,
    "x" : 0,
    "cfg_blk_index" : 3,
    "id" : 3
  }, {
    "module_id" : 1,
    "type" : "IB",
    "y" : 8,
    "x" : 0,
    "cfg_blk_index" : 4,
    "id" : 4
  }, {
    "module_id" : 1,
    "type" : "IB",
    "y" : 2,
    "x" : 21,
    "cfg_blk_index" : 127,
    "id" : 127
  }, {
    "module_id" : 1,
    "type" : "IB",
    "y" : 4,
    "x" : 21,
    "cfg_blk_index" : 128,
    "id" : 128
  }, {
    "module_id" : 1,
    "type" : "IB",
    "y" : 6,
    "x" : 21,
    "cfg_blk_index" : 129,
    "id" : 129
  }, {
    "module_id" : 1,
    "type" : "IB",
    "y" : 8,
    "x" : 21,
    "cfg_blk_index" : 130,
    "id" : 130
  }, {
    "type" : "This",
    "id" : 0
  }, {
    "module_id" : 13,
    "type" : "LSU",
    "y" : 0,
    "x" : 3,
    "lsu_id" : 0,
    "cfg_blk_index" : 19,
    "id" : 19
  }, {
    "module_id" : 13,
    "type" : "LSU",
    "y" : 10,
    "x" : 3,
    "lsu_id" : 1,
    "cfg_blk_index" : 24,
    "id" : 24
  }, {
    "module_id" : 13,
    "type" : "LSU",
    "y" : 0,
    "x" : 5,
    "lsu_id" : 2,
    "cfg_blk_index" : 31,
    "id" : 31
  }, {
    "module_id" : 13,
    "type" : "LSU",
    "y" : 10,
    "x" : 5,
    "lsu_id" : 3,
    "cfg_blk_index" : 36,
    "id" : 36
  }, {
    "module_id" : 13,
    "type" : "LSU",
    "y" : 0,
    "x" : 7,
    "lsu_id" : 4,
    "cfg_blk_index" : 43,
    "id" : 43
  }, {
    "module_id" : 13,
    "type" : "LSU",
    "y" : 10,
    "x" : 7,
    "lsu_id" : 5,
    "cfg_blk_index" : 48,
    "id" : 48
  }, {
    "module_id" : 13,
    "type" : "LSU",
    "y" : 0,
    "x" : 9,
    "lsu_id" : 6,
    "cfg_blk_index" : 55,
    "id" : 55
  }, {
    "module_id" : 13,
    "type" : "LSU",
    "y" : 10,
    "x" : 9,
    "lsu_id" : 7,
    "cfg_blk_index" : 60,
    "id" : 60
  }, {
    "module_id" : 13,
    "type" : "LSU",
    "y" : 0,
    "x" : 11,
    "lsu_id" : 8,
    "cfg_blk_index" : 67,
    "id" : 67
  }, {
    "module_id" : 13,
    "type" : "LSU",
    "y" : 10,
    "x" : 11,
    "lsu_id" : 9,
    "cfg_blk_index" : 72,
    "id" : 72
  }, {
    "module_id" : 13,
    "type" : "LSU",
    "y" : 0,
    "x" : 13,
    "lsu_id" : 10,
    "cfg_blk_index" : 79,
    "id" : 79
  }, {
    "module_id" : 13,
    "type" : "LSU",
    "y" : 10,
    "x" : 13,
    "lsu_id" : 11,
    "cfg_blk_index" : 84,
    "id" : 84
  }, {
    "module_id" : 13,
    "type" : "LSU",
    "y" : 0,
    "x" : 15,
    "lsu_id" : 12,
    "cfg_blk_index" : 91,
    "id" : 91
  }, {
    "module_id" : 13,
    "type" : "LSU",
    "y" : 10,
    "x" : 15,
    "lsu_id" : 13,
    "cfg_blk_index" : 96,
    "id" : 96
  }, {
    "module_id" : 13,
    "type" : "LSU",
    "y" : 0,
    "x" : 17,
    "lsu_id" : 14,
    "cfg_blk_index" : 103,
    "id" : 103
  }, {
    "module_id" : 13,
    "type" : "LSU",
    "y" : 10,
    "x" : 17,
    "lsu_id" : 15,
    "cfg_blk_index" : 108,
    "id" : 108
  }, {
    "module_id" : 13,
    "type" : "LSU",
    "y" : 0,
    "x" : 19,
    "lsu_id" : 16,
    "cfg_blk_index" : 115,
    "id" : 115
  }, {
    "module_id" : 13,
    "type" : "LSU",
    "y" : 10,
    "x" : 19,
    "lsu_id" : 17,
    "cfg_blk_index" : 120,
    "id" : 120
  }, {
    "module_id" : 3,
    "type" : "GPE",
    "y" : 2,
    "x" : 3,
    "cfg_blk_index" : 20,
    "id" : 20
  }, {
    "module_id" : 3,
    "type" : "GPE",
    "y" : 4,
    "x" : 3,
    "cfg_blk_index" : 21,
    "id" : 21
  }, {
    "module_id" : 3,
    "type" : "GPE",
    "y" : 6,
    "x" : 3,
    "cfg_blk_index" : 22,
    "id" : 22
  }, {
    "module_id" : 3,
    "type" : "GPE",
    "y" : 8,
    "x" : 3,
    "cfg_blk_index" : 23,
    "id" : 23
  }, {
    "module_id" : 3,
    "type" : "GPE",
    "y" : 2,
    "x" : 5,
    "cfg_blk_index" : 32,
    "id" : 32
  }, {
    "module_id" : 3,
    "type" : "GPE",
    "y" : 4,
    "x" : 5,
    "cfg_blk_index" : 33,
    "id" : 33
  }, {
    "module_id" : 3,
    "type" : "GPE",
    "y" : 6,
    "x" : 5,
    "cfg_blk_index" : 34,
    "id" : 34
  }, {
    "module_id" : 3,
    "type" : "GPE",
    "y" : 8,
    "x" : 5,
    "cfg_blk_index" : 35,
    "id" : 35
  }, {
    "module_id" : 3,
    "type" : "GPE",
    "y" : 2,
    "x" : 7,
    "cfg_blk_index" : 44,
    "id" : 44
  }, {
    "module_id" : 3,
    "type" : "GPE",
    "y" : 4,
    "x" : 7,
    "cfg_blk_index" : 45,
    "id" : 45
  }, {
    "module_id" : 3,
    "type" : "GPE",
    "y" : 6,
    "x" : 7,
    "cfg_blk_index" : 46,
    "id" : 46
  }, {
    "module_id" : 3,
    "type" : "GPE",
    "y" : 8,
    "x" : 7,
    "cfg_blk_index" : 47,
    "id" : 47
  }, {
    "module_id" : 3,
    "type" : "GPE",
    "y" : 2,
    "x" : 9,
    "cfg_blk_index" : 56,
    "id" : 56
  }, {
    "module_id" : 3,
    "type" : "GPE",
    "y" : 4,
    "x" : 9,
    "cfg_blk_index" : 57,
    "id" : 57
  }, {
    "module_id" : 3,
    "type" : "GPE",
    "y" : 6,
    "x" : 9,
    "cfg_blk_index" : 58,
    "id" : 58
  }, {
    "module_id" : 3,
    "type" : "GPE",
    "y" : 8,
    "x" : 9,
    "cfg_blk_index" : 59,
    "id" : 59
  }, {
    "module_id" : 3,
    "type" : "GPE",
    "y" : 2,
    "x" : 11,
    "cfg_blk_index" : 68,
    "id" : 68
  }, {
    "module_id" : 3,
    "type" : "GPE",
    "y" : 4,
    "x" : 11,
    "cfg_blk_index" : 69,
    "id" : 69
  }, {
    "module_id" : 3,
    "type" : "GPE",
    "y" : 6,
    "x" : 11,
    "cfg_blk_index" : 70,
    "id" : 70
  }, {
    "module_id" : 3,
    "type" : "GPE",
    "y" : 8,
    "x" : 11,
    "cfg_blk_index" : 71,
    "id" : 71
  }, {
    "module_id" : 3,
    "type" : "GPE",
    "y" : 2,
    "x" : 13,
    "cfg_blk_index" : 80,
    "id" : 80
  }, {
    "module_id" : 3,
    "type" : "GPE",
    "y" : 4,
    "x" : 13,
    "cfg_blk_index" : 81,
    "id" : 81
  }, {
    "module_id" : 3,
    "type" : "GPE",
    "y" : 6,
    "x" : 13,
    "cfg_blk_index" : 82,
    "id" : 82
  }, {
    "module_id" : 3,
    "type" : "GPE",
    "y" : 8,
    "x" : 13,
    "cfg_blk_index" : 83,
    "id" : 83
  }, {
    "module_id" : 3,
    "type" : "GPE",
    "y" : 2,
    "x" : 15,
    "cfg_blk_index" : 92,
    "id" : 92
  }, {
    "module_id" : 3,
    "type" : "GPE",
    "y" : 4,
    "x" : 15,
    "cfg_blk_index" : 93,
    "id" : 93
  }, {
    "module_id" : 3,
    "type" : "GPE",
    "y" : 6,
    "x" : 15,
    "cfg_blk_index" : 94,
    "id" : 94
  }, {
    "module_id" : 3,
    "type" : "GPE",
    "y" : 8,
    "x" : 15,
    "cfg_blk_index" : 95,
    "id" : 95
  }, {
    "module_id" : 3,
    "type" : "GPE",
    "y" : 2,
    "x" : 17,
    "cfg_blk_index" : 104,
    "id" : 104
  }, {
    "module_id" : 3,
    "type" : "GPE",
    "y" : 4,
    "x" : 17,
    "cfg_blk_index" : 105,
    "id" : 105
  }, {
    "module_id" : 3,
    "type" : "GPE",
    "y" : 6,
    "x" : 17,
    "cfg_blk_index" : 106,
    "id" : 106
  }, {
    "module_id" : 3,
    "type" : "GPE",
    "y" : 8,
    "x" : 17,
    "cfg_blk_index" : 107,
    "id" : 107
  }, {
    "module_id" : 3,
    "type" : "GPE",
    "y" : 2,
    "x" : 19,
    "cfg_blk_index" : 116,
    "id" : 116
  }, {
    "module_id" : 3,
    "type" : "GPE",
    "y" : 4,
    "x" : 19,
    "cfg_blk_index" : 117,
    "id" : 117
  }, {
    "module_id" : 3,
    "type" : "GPE",
    "y" : 6,
    "x" : 19,
    "cfg_blk_index" : 118,
    "id" : 118
  }, {
    "module_id" : 3,
    "type" : "GPE",
    "y" : 8,
    "x" : 19,
    "cfg_blk_index" : 119,
    "id" : 119
  }, {
    "module_id" : 2,
    "type" : "OB",
    "y" : 2,
    "x" : 1,
    "cfg_blk_index" : 7,
    "id" : 7
  }, {
    "module_id" : 2,
    "type" : "OB",
    "y" : 4,
    "x" : 1,
    "cfg_blk_index" : 8,
    "id" : 8
  }, {
    "module_id" : 2,
    "type" : "OB",
    "y" : 6,
    "x" : 1,
    "cfg_blk_index" : 9,
    "id" : 9
  }, {
    "module_id" : 2,
    "type" : "OB",
    "y" : 8,
    "x" : 1,
    "cfg_blk_index" : 10,
    "id" : 10
  }, {
    "module_id" : 2,
    "type" : "OB",
    "y" : 2,
    "x" : 22,
    "cfg_blk_index" : 133,
    "id" : 133
  }, {
    "module_id" : 2,
    "type" : "OB",
    "y" : 4,
    "x" : 22,
    "cfg_blk_index" : 134,
    "id" : 134
  }, {
    "module_id" : 2,
    "type" : "OB",
    "y" : 6,
    "x" : 22,
    "cfg_blk_index" : 135,
    "id" : 135
  }, {
    "module_id" : 2,
    "type" : "OB",
    "y" : 8,
    "x" : 22,
    "cfg_blk_index" : 136,
    "id" : 136
  } ],
  "num_output_ob" : 1,
  "num_input" : 8,
  "connections" : {
    "645" : [ 112, "GIB", 3, 124, "GIB", 1 ],
    "69" : [ 21, "GPE", 0, 15, "GIB", 7 ],
    "629" : [ 112, "GIB", 0, 111, "GIB", 2 ],
    "365" : [ 88, "GIB", 11, 94, "GPE", 5 ],
    "138" : [ 40, "GIB", 7, 35, "GPE", 6 ],
    "101" : [ 26, "GIB", 11, 32, "GPE", 5 ],
    "479" : [ 119, "GPE", 0, 125, "GIB", 4 ],
    "347" : [ 92, "GPE", 0, 98, "GIB", 4 ],
    "333" : [ 83, "GPE", 0, 77, "GIB", 7 ],
    "628" : [ 110, "GIB", 2, 111, "GIB", 0 ],
    "249" : [ 68, "GPE", 0, 62, "GIB", 7 ],
    "518" : [ 27, "GIB", 3, 39, "GIB", 1 ],
    "468" : [ 112, "GIB", 8, 119, "GPE", 0 ],
    "234" : [ 64, "GIB", 7, 59, "GPE", 6 ],
    "0" : [ 0, "This", 0, 1, "IB", 0 ],
    "555" : [ 75, "GIB", 1, 63, "GIB", 3 ],
    "666" : [ 37, "GIB", 9, 43, "LSU", 0 ],
    "88" : [ 16, "GIB", 7, 23, "GPE", 4 ],
    "481" : [ 14, "GIB", 0, 13, "GIB", 2 ],
    "352" : [ 86, "GIB", 9, 93, "GPE", 4 ],
    "408" : [ 99, "GIB", 8, 106, "GPE", 0 ],
    "170" : [ 51, "GIB", 6, 46, "GPE", 2 ],
    "523" : [ 52, "GIB", 1, 40, "GIB", 3 ],
    "582" : [ 76, "GIB", 2, 77, "GIB", 0 ],
    "115" : [ 39, "GIB", 5, 33, "GPE", 7 ],
    "683" : [ 73, "GIB", 4, 67, "LSU", 1 ],
    "217" : [ 52, "GIB", 10, 58, "GPE", 1 ],
    "276" : [ 64, "GIB", 8, 71, "GPE", 0 ],
    "308" : [ 81, "GPE", 0, 74, "GIB", 6 ],
    "5" : [ 2, "IB", 0, 15, "GIB", 4 ],
    "449" : [ 111, "GIB", 11, 117, "GPE", 5 ],
    "120" : [ 27, "GIB", 8, 34, "GPE", 0 ],
    "247" : [ 74, "GIB", 5, 68, "GPE", 7 ],
    "379" : [ 101, "GIB", 5, 95, "GPE", 7 ],
    "440" : [ 116, "GPE", 0, 109, "GIB", 6 ],
    "655" : [ 29, "GIB", 6, 24, "LSU", 1 ],
    "511" : [ 25, "GIB", 3, 37, "GIB", 1 ],
    "614" : [ 99, "GIB", 2, 100, "GIB", 0 ],
    "269" : [ 64, "GIB", 11, 70, "GPE", 5 ],
    "677" : [ 55, "LSU", 0, 61, "GIB", 4 ],
    "202" : [ 56, "GPE", 0, 61, "GIB", 5 ],
    "597" : [ 89, "GIB", 0, 88, "GIB", 2 ],
    "10" : [ 4, "IB", 0, 16, "GIB", 5 ],
    "385" : [ 98, "GIB", 10, 104, "GPE", 1 ],
    "384" : [ 97, "GIB", 7, 104, "GPE", 0 ],
    "56" : [ 20, "GPE", 0, 13, "GIB", 5 ],
    "533" : [ 62, "GIB", 1, 50, "GIB", 3 ],
    "550" : [ 50, "GIB", 3, 62, "GIB", 1 ],
    "142" : [ 35, "GPE", 0, 40, "GIB", 5 ],
    "500" : [ 15, "GIB", 3, 27, "GIB", 1 ],
    "715" : [ 121, "GIB", 4, 115, "LSU", 1 ],
    "472" : [ 112, "GIB", 9, 119, "GPE", 4 ],
    "698" : [ 85, "GIB", 9, 91, "LSU", 0 ],
    "340" : [ 85, "GIB", 8, 92, "GPE", 4 ],
    "538" : [ 50, "GIB", 2, 51, "GIB", 0 ],
    "153" : [ 44, "GPE", 0, 38, "GIB", 7 ],
    "670" : [ 41, "GIB", 7, 48, "LSU", 0 ],
    "174" : [ 51, "GIB", 7, 46, "GPE", 6 ],
    "404" : [ 105, "GPE", 0, 98, "GIB", 6 ],
    "185" : [ 41, "GIB", 9, 47, "GPE", 5 ],
    "42" : [ 135, "OB", 0, 0, "This", 6 ],
    "709" : [ 103, "LSU", 0, 109, "GIB", 4 ],
    "417" : [ 106, "GPE", 0, 100, "GIB", 7 ],
    "24" : [ 7, "OB", 0, 0, "This", 0 ],
    "288" : [ 73, "GIB", 7, 80, "GPE", 0 ],
    "301" : [ 75, "GIB", 10, 81, "GPE", 1 ],
    "320" : [ 82, "GPE", 0, 75, "GIB", 6 ],
    "565" : [ 61, "GIB", 3, 73, "GIB", 1 ],
    "436" : [ 109, "GIB", 8, 116, "GPE", 4 ],
    "37" : [ 121, "GIB", 7, 133, "OB", 0 ],
    "25" : [ 13, "GIB", 4, 7, "OB", 0 ],
    "651" : [ 25, "GIB", 4, 19, "LSU", 1 ],
    "257" : [ 63, "GIB", 11, 69, "GPE", 5 ],
    "389" : [ 98, "GIB", 11, 104, "GPE", 5 ],
    "52" : [ 13, "GIB", 6, 20, "GPE", 4 ],
    "14" : [ 127, "IB", 0, 122, "GIB", 7 ],
    "570" : [ 73, "GIB", 2, 74, "GIB", 0 ],
    "184" : [ 40, "GIB", 9, 47, "GPE", 4 ],
    "719" : [ 125, "GIB", 6, 120, "LSU", 1 ],
    "372" : [ 88, "GIB", 8, 95, "GPE", 0 ],
    "504" : [ 16, "GIB", 3, 28, "GIB", 1 ],
    "110" : [ 38, "GIB", 6, 33, "GPE", 2 ],
    "587" : [ 98, "GIB", 1, 86, "GIB", 3 ],
    "619" : [ 97, "GIB", 3, 109, "GIB", 1 ],
    "702" : [ 89, "GIB", 7, 96, "LSU", 0 ],
    "125" : [ 28, "GIB", 11, 34, "GPE", 5 ],
    "344" : [ 92, "GPE", 0, 85, "GIB", 6 ],
    "357" : [ 93, "GPE", 0, 87, "GIB", 7 ],
    "196" : [ 49, "GIB", 8, 56, "GPE", 4 ],
    "542" : [ 51, "GIB", 2, 52, "GIB", 0 ],
    "460" : [ 111, "GIB", 9, 118, "GPE", 4 ],
    "157" : [ 39, "GIB", 10, 45, "GPE", 1 ],
    "559" : [ 76, "GIB", 1, 64, "GIB", 3 ],
    "638" : [ 122, "GIB", 0, 121, "GIB", 2 ],
    "189" : [ 47, "GPE", 0, 41, "GIB", 7 ],
    "20" : [ 129, "IB", 0, 124, "GIB", 7 ],
    "421" : [ 101, "GIB", 8, 107, "GPE", 1 ],
    "46" : [ 124, "GIB", 8, 136, "OB", 0 ],
    "93" : [ 23, "GPE", 0, 17, "GIB", 6 ],
    "606" : [ 97, "GIB", 2, 98, "GIB", 0 ],
    "284" : [ 71, "GPE", 0, 64, "GIB", 6 ],
    "416" : [ 106, "GPE", 0, 99, "GIB", 6 ],
    "325" : [ 77, "GIB", 8, 83, "GPE", 1 ],
    "152" : [ 44, "GPE", 0, 37, "GIB", 6 ],
    "228" : [ 52, "GIB", 8, 59, "GPE", 0 ],
    "289" : [ 74, "GIB", 10, 80, "GPE", 1 ],
    "448" : [ 110, "GIB", 9, 117, "GPE", 4 ],
    "57" : [ 20, "GPE", 0, 14, "GIB", 7 ],
    "316" : [ 75, "GIB", 9, 82, "GPE", 4 ],
    "78" : [ 27, "GIB", 7, 22, "GPE", 6 ],
    "261" : [ 69, "GPE", 0, 63, "GIB", 7 ],
    "29" : [ 15, "GIB", 4, 8, "OB", 1 ],
    "216" : [ 51, "GIB", 8, 58, "GPE", 0 ],
    "475" : [ 125, "GIB", 5, 119, "GPE", 7 ],
    "492" : [ 16, "GIB", 2, 17, "GIB", 0 ],
    "164" : [ 45, "GPE", 0, 38, "GIB", 6 ],
    "179" : [ 46, "GPE", 0, 52, "GIB", 4 ],
    "591" : [ 99, "GIB", 1, 87, "GIB", 3 ],
    "443" : [ 116, "GPE", 0, 122, "GIB", 4 ],
    "321" : [ 82, "GPE", 0, 76, "GIB", 7 ],
    "376" : [ 88, "GIB", 9, 95, "GPE", 4 ],
    "623" : [ 122, "GIB", 1, 110, "GIB", 3 ],
    "211" : [ 63, "GIB", 5, 57, "GPE", 7 ],
    "646" : [ 123, "GIB", 2, 124, "GIB", 0 ],
    "253" : [ 63, "GIB", 10, 69, "GPE", 1 ],
    "485" : [ 27, "GIB", 1, 15, "GIB", 3 ],
    "106" : [ 32, "GPE", 0, 37, "GIB", 5 ],
    "238" : [ 59, "GPE", 0, 64, "GIB", 5 ],
    "121" : [ 28, "GIB", 10, 34, "GPE", 1 ],
    "514" : [ 26, "GIB", 3, 38, "GIB", 1 ],
    "348" : [ 86, "GIB", 8, 93, "GPE", 0 ],
    "574" : [ 74, "GIB", 2, 75, "GIB", 0 ],
    "84" : [ 16, "GIB", 6, 23, "GPE", 0 ],
    "353" : [ 87, "GIB", 11, 93, "GPE", 5 ],
    "480" : [ 25, "GIB", 1, 13, "GIB", 3 ],
    "602" : [ 109, "GIB", 1, 97, "GIB", 3 ],
    "147" : [ 50, "GIB", 4, 44, "GPE", 3 ],
    "397" : [ 99, "GIB", 10, 105, "GPE", 1 ],
    "687" : [ 77, "GIB", 6, 72, "LSU", 1 ],
    "280" : [ 64, "GIB", 9, 71, "GPE", 4 ],
    "61" : [ 15, "GIB", 8, 21, "GPE", 1 ],
    "634" : [ 101, "GIB", 3, 113, "GIB", 1 ],
    "692" : [ 79, "LSU", 0, 73, "GIB", 7 ],
    "221" : [ 52, "GIB", 11, 58, "GPE", 5 ],
    "293" : [ 74, "GIB", 11, 80, "GPE", 5 ],
    "453" : [ 117, "GPE", 0, 111, "GIB", 7 ],
    "132" : [ 28, "GIB", 8, 35, "GPE", 0 ],
    "396" : [ 98, "GIB", 8, 105, "GPE", 0 ],
    "89" : [ 17, "GIB", 7, 23, "GPE", 5 ],
    "133" : [ 29, "GIB", 8, 35, "GPE", 1 ],
    "660" : [ 31, "LSU", 0, 25, "GIB", 7 ],
    "411" : [ 112, "GIB", 4, 106, "GPE", 3 ],
    "116" : [ 33, "GPE", 0, 26, "GIB", 6 ],
    "243" : [ 74, "GIB", 4, 68, "GPE", 3 ],
    "428" : [ 107, "GPE", 0, 100, "GIB", 6 ],
    "1" : [ 1, "IB", 0, 13, "GIB", 4 ],
    "265" : [ 64, "GIB", 10, 70, "GPE", 1 ],
    "507" : [ 29, "GIB", 0, 28, "GIB", 2 ],
    "527" : [ 53, "GIB", 1, 41, "GIB", 3 ],
    "312" : [ 75, "GIB", 8, 82, "GPE", 0 ],
    "74" : [ 27, "GIB", 6, 22, "GPE", 2 ],
    "206" : [ 62, "GIB", 6, 57, "GPE", 2 ],
    "307" : [ 87, "GIB", 5, 81, "GPE", 7 ],
    "292" : [ 73, "GIB", 8, 80, "GPE", 4 ],
    "233" : [ 53, "GIB", 9, 59, "GPE", 5 ],
    "452" : [ 117, "GPE", 0, 110, "GIB", 6 ],
    "6" : [ 0, "This", 2, 3, "IB", 0 ],
    "248" : [ 68, "GPE", 0, 61, "GIB", 6 ],
    "60" : [ 14, "GIB", 6, 21, "GPE", 0 ],
    "380" : [ 95, "GPE", 0, 88, "GIB", 6 ],
    "117" : [ 33, "GPE", 0, 27, "GIB", 7 ],
    "512" : [ 49, "GIB", 1, 37, "GIB", 3 ],
    "439" : [ 122, "GIB", 5, 116, "GPE", 7 ],
    "678" : [ 53, "GIB", 7, 60, "LSU", 0 ],
    "270" : [ 75, "GIB", 7, 70, "GPE", 6 ],
    "529" : [ 37, "GIB", 3, 49, "GIB", 1 ],
    "661" : [ 31, "LSU", 0, 37, "GIB", 4 ],
    "546" : [ 52, "GIB", 2, 53, "GIB", 0 ],
    "85" : [ 17, "GIB", 6, 23, "GPE", 1 ],
    "201" : [ 56, "GPE", 0, 50, "GIB", 7 ],
    "381" : [ 95, "GPE", 0, 89, "GIB", 7 ],
    "220" : [ 51, "GIB", 9, 58, "GPE", 4 ],
    "366" : [ 99, "GIB", 7, 94, "GPE", 6 ],
    "534" : [ 49, "GIB", 2, 50, "GIB", 0 ],
    "102" : [ 37, "GIB", 6, 32, "GPE", 6 ],
    "714" : [ 109, "GIB", 9, 115, "LSU", 0 ],
    "334" : [ 83, "GPE", 0, 88, "GIB", 5 ],
    "302" : [ 86, "GIB", 6, 81, "GPE", 2 ],
    "260" : [ 69, "GPE", 0, 62, "GIB", 6 ],
    "349" : [ 87, "GIB", 10, 93, "GPE", 1 ],
    "28" : [ 14, "GIB", 5, 8, "OB", 0 ],
    "38" : [ 122, "GIB", 9, 133, "OB", 1 ],
    "598" : [ 77, "GIB", 3, 89, "GIB", 1 ],
    "160" : [ 38, "GIB", 9, 45, "GPE", 4 ],
    "561" : [ 65, "GIB", 0, 64, "GIB", 2 ],
    "392" : [ 104, "GPE", 0, 97, "GIB", 6 ],
    "297" : [ 80, "GPE", 0, 74, "GIB", 7 ],
    "70" : [ 21, "GPE", 0, 26, "GIB", 5 ],
    "424" : [ 100, "GIB", 9, 107, "GPE", 4 ],
    "192" : [ 49, "GIB", 7, 56, "GPE", 0 ],
    "407" : [ 105, "GPE", 0, 111, "GIB", 4 ],
    "693" : [ 79, "LSU", 0, 85, "GIB", 4 ],
    "630" : [ 100, "GIB", 3, 112, "GIB", 1 ],
    "429" : [ 107, "GPE", 0, 101, "GIB", 7 ],
    "275" : [ 70, "GPE", 0, 76, "GIB", 4 ],
    "21" : [ 0, "This", 7, 130, "IB", 0 ],
    "137" : [ 29, "GIB", 9, 35, "GPE", 5 ],
    "165" : [ 45, "GPE", 0, 39, "GIB", 7 ],
    "33" : [ 10, "OB", 0, 0, "This", 3 ],
    "92" : [ 23, "GPE", 0, 16, "GIB", 6 ],
    "467" : [ 118, "GPE", 0, 124, "GIB", 4 ],
    "229" : [ 53, "GIB", 8, 59, "GPE", 1 ],
    "566" : [ 85, "GIB", 1, 73, "GIB", 3 ],
    "484" : [ 15, "GIB", 0, 14, "GIB", 2 ],
    "252" : [ 62, "GIB", 8, 69, "GPE", 0 ],
    "197" : [ 50, "GIB", 11, 56, "GPE", 5 ],
    "361" : [ 88, "GIB", 10, 94, "GPE", 1 ],
    "65" : [ 15, "GIB", 9, 21, "GPE", 5 ],
    "625" : [ 111, "GIB", 0, 110, "GIB", 2 ],
    "435" : [ 122, "GIB", 4, 116, "GPE", 3 ],
    "97" : [ 26, "GIB", 10, 32, "GPE", 1 ],
    "329" : [ 77, "GIB", 9, 83, "GPE", 5 ],
    "665" : [ 36, "LSU", 0, 41, "GIB", 5 ],
    "583" : [ 73, "GIB", 3, 85, "GIB", 1 ],
    "522" : [ 28, "GIB", 3, 40, "GIB", 1 ],
    "461" : [ 112, "GIB", 11, 118, "GPE", 5 ],
    "493" : [ 13, "GIB", 3, 25, "GIB", 1 ],
    "682" : [ 61, "GIB", 9, 67, "LSU", 0 ],
    "551" : [ 74, "GIB", 1, 62, "GIB", 3 ],
    "710" : [ 101, "GIB", 7, 108, "LSU", 0 ],
    "456" : [ 111, "GIB", 8, 118, "GPE", 0 ],
    "324" : [ 76, "GIB", 8, 83, "GPE", 0 ],
    "285" : [ 71, "GPE", 0, 65, "GIB", 7 ],
    "224" : [ 58, "GPE", 0, 51, "GIB", 6 ],
    "519" : [ 51, "GIB", 1, 39, "GIB", 3 ],
    "578" : [ 75, "GIB", 2, 76, "GIB", 0 ],
    "697" : [ 84, "LSU", 0, 89, "GIB", 5 ],
    "317" : [ 76, "GIB", 11, 82, "GPE", 5 ],
    "650" : [ 13, "GIB", 7, 19, "LSU", 0 ],
    "156" : [ 38, "GIB", 8, 45, "GPE", 0 ],
    "615" : [ 101, "GIB", 0, 100, "GIB", 2 ],
    "403" : [ 111, "GIB", 5, 105, "GPE", 7 ],
    "9" : [ 0, "This", 3, 4, "IB", 0 ],
    "188" : [ 47, "GPE", 0, 40, "GIB", 6 ],
    "388" : [ 97, "GIB", 8, 104, "GPE", 4 ],
    "53" : [ 14, "GIB", 9, 20, "GPE", 5 ],
    "356" : [ 93, "GPE", 0, 86, "GIB", 6 ],
    "169" : [ 40, "GIB", 10, 46, "GPE", 1 ],
    "593" : [ 88, "GIB", 0, 87, "GIB", 2 ],
    "141" : [ 35, "GPE", 0, 29, "GIB", 7 ],
    "610" : [ 98, "GIB", 2, 99, "GIB", 0 ],
    "420" : [ 100, "GIB", 8, 107, "GPE", 0 ],
    "499" : [ 27, "GIB", 0, 26, "GIB", 2 ],
    "109" : [ 27, "GIB", 10, 33, "GPE", 1 ],
    "328" : [ 76, "GIB", 9, 83, "GPE", 4 ],
    "471" : [ 125, "GIB", 4, 119, "GPE", 3 ],
    "256" : [ 62, "GIB", 9, 69, "GPE", 4 ],
    "488" : [ 28, "GIB", 1, 16, "GIB", 3 ],
    "124" : [ 27, "GIB", 9, 34, "GPE", 4 ],
    "225" : [ 58, "GPE", 0, 52, "GIB", 7 ],
    "339" : [ 98, "GIB", 4, 92, "GPE", 3 ],
    "77" : [ 16, "GIB", 9, 22, "GPE", 5 ],
    "554" : [ 51, "GIB", 3, 63, "GIB", 1 ],
    "193" : [ 50, "GIB", 10, 56, "GPE", 1 ],
    "537" : [ 63, "GIB", 1, 51, "GIB", 3 ],
    "669" : [ 43, "LSU", 0, 49, "GIB", 4 ],
    "686" : [ 65, "GIB", 7, 72, "LSU", 0 ],
    "476" : [ 119, "GPE", 0, 112, "GIB", 6 ],
    "642" : [ 111, "GIB", 3, 123, "GIB", 1 ],
    "526" : [ 29, "GIB", 3, 41, "GIB", 1 ],
    "637" : [ 109, "GIB", 3, 121, "GIB", 1 ],
    "489" : [ 15, "GIB", 2, 16, "GIB", 0 ],
    "590" : [ 75, "GIB", 3, 87, "GIB", 1 ],
    "679" : [ 65, "GIB", 6, 60, "LSU", 1 ],
    "547" : [ 49, "GIB", 3, 61, "GIB", 1 ],
    "212" : [ 57, "GPE", 0, 50, "GIB", 6 ],
    "706" : [ 97, "GIB", 9, 103, "LSU", 0 ],
    "96" : [ 25, "GIB", 7, 32, "GPE", 0 ],
    "622" : [ 98, "GIB", 3, 110, "GIB", 1 ],
    "393" : [ 104, "GPE", 0, 98, "GIB", 7 ],
    "647" : [ 125, "GIB", 0, 124, "GIB", 2 ],
    "701" : [ 91, "LSU", 0, 97, "GIB", 4 ],
    "515" : [ 50, "GIB", 1, 38, "GIB", 3 ],
    "654" : [ 17, "GIB", 5, 24, "LSU", 0 ],
    "457" : [ 112, "GIB", 10, 118, "GPE", 1 ],
    "173" : [ 40, "GIB", 11, 46, "GPE", 5 ],
    "721" : [ 120, "LSU", 0, 125, "GIB", 5 ],
    "13" : [ 127, "IB", 0, 121, "GIB", 6 ],
    "129" : [ 34, "GPE", 0, 28, "GIB", 7 ],
    "569" : [ 86, "GIB", 1, 74, "GIB", 3 ],
    "41" : [ 123, "GIB", 9, 134, "OB", 1 ],
    "371" : [ 94, "GPE", 0, 100, "GIB", 4 ],
    "503" : [ 28, "GIB", 0, 27, "GIB", 2 ],
    "605" : [ 110, "GIB", 1, 98, "GIB", 3 ],
    "134" : [ 40, "GIB", 6, 35, "GPE", 2 ],
    "73" : [ 16, "GIB", 8, 22, "GPE", 1 ],
    "128" : [ 34, "GPE", 0, 27, "GIB", 6 ],
    "343" : [ 98, "GIB", 5, 92, "GPE", 7 ],
    "237" : [ 59, "GPE", 0, 53, "GIB", 7 ],
    "105" : [ 32, "GPE", 0, 26, "GIB", 7 ],
    "244" : [ 61, "GIB", 8, 68, "GPE", 4 ],
    "2" : [ 1, "IB", 0, 14, "GIB", 4 ],
    "266" : [ 75, "GIB", 6, 70, "GPE", 2 ],
    "633" : [ 113, "GIB", 0, 112, "GIB", 2 ],
    "360" : [ 87, "GIB", 8, 94, "GPE", 0 ],
    "205" : [ 51, "GIB", 10, 57, "GPE", 1 ],
    "508" : [ 17, "GIB", 3, 29, "GIB", 1 ],
    "311" : [ 81, "GPE", 0, 87, "GIB", 4 ],
    "541" : [ 64, "GIB", 1, 52, "GIB", 3 ],
    "657" : [ 24, "LSU", 0, 29, "GIB", 5 ],
    "398" : [ 110, "GIB", 6, 105, "GPE", 2 ],
    "558" : [ 52, "GIB", 3, 64, "GIB", 1 ],
    "674" : [ 49, "GIB", 9, 55, "LSU", 0 ],
    "530" : [ 61, "GIB", 1, 49, "GIB", 3 ],
    "586" : [ 74, "GIB", 3, 86, "GIB", 1 ],
    "662" : [ 29, "GIB", 7, 36, "LSU", 0 ],
    "718" : [ 113, "GIB", 7, 120, "LSU", 0 ],
    "298" : [ 80, "GPE", 0, 85, "GIB", 5 ],
    "412" : [ 99, "GIB", 9, 106, "GPE", 4 ],
    "618" : [ 100, "GIB", 2, 101, "GIB", 0 ],
    "425" : [ 101, "GIB", 9, 107, "GPE", 5 ],
    "513" : [ 38, "GIB", 0, 37, "GIB", 2 ],
    "430" : [ 107, "GPE", 0, 112, "GIB", 5 ],
    "166" : [ 45, "GPE", 0, 50, "GIB", 5 ],
    "32" : [ 16, "GIB", 4, 9, "OB", 1 ],
    "34" : [ 16, "GIB", 5, 10, "OB", 0 ],
    "148" : [ 37, "GIB", 8, 44, "GPE", 4 ],
    "264" : [ 63, "GIB", 8, 70, "GPE", 0 ],
    "45" : [ 136, "OB", 0, 0, "This", 7 ],
    "161" : [ 39, "GIB", 11, 45, "GPE", 5 ],
    "279" : [ 77, "GIB", 4, 71, "GPE", 3 ],
    "64" : [ 14, "GIB", 7, 21, "GPE", 4 ],
    "573" : [ 87, "GIB", 1, 75, "GIB", 3 ],
    "180" : [ 40, "GIB", 8, 47, "GPE", 0 ],
    "689" : [ 72, "LSU", 0, 77, "GIB", 5 ],
    "296" : [ 80, "GPE", 0, 73, "GIB", 6 ],
    "17" : [ 128, "IB", 0, 123, "GIB", 7 ],
    "444" : [ 110, "GIB", 8, 117, "GPE", 0 ],
    "149" : [ 38, "GIB", 11, 44, "GPE", 5 ],
    "375" : [ 101, "GIB", 4, 95, "GPE", 3 ],
    "601" : [ 85, "GIB", 3, 97, "GIB", 1 ],
    "584" : [ 97, "GIB", 1, 85, "GIB", 3 ],
    "562" : [ 53, "GIB", 3, 65, "GIB", 1 ],
    "176" : [ 46, "GPE", 0, 39, "GIB", 6 ],
    "423" : [ 113, "GIB", 4, 107, "GPE", 3 ],
    "694" : [ 77, "GIB", 7, 84, "LSU", 0 ],
    "191" : [ 47, "GPE", 0, 53, "GIB", 4 ],
    "402" : [ 110, "GIB", 7, 105, "GPE", 6 ],
    "22" : [ 130, "IB", 0, 124, "GIB", 6 ],
    "44" : [ 124, "GIB", 9, 135, "OB", 1 ],
    "286" : [ 71, "GPE", 0, 76, "GIB", 5 ],
    "577" : [ 88, "GIB", 1, 76, "GIB", 3 ],
    "711" : [ 113, "GIB", 6, 108, "LSU", 1 ],
    "579" : [ 77, "GIB", 0, 76, "GIB", 2 ],
    "291" : [ 86, "GIB", 4, 80, "GPE", 3 ],
    "59" : [ 20, "GPE", 0, 26, "GIB", 4 ],
    "118" : [ 33, "GPE", 0, 38, "GIB", 5 ],
    "281" : [ 65, "GIB", 9, 71, "GPE", 5 ],
    "204" : [ 50, "GIB", 8, 57, "GPE", 0 ],
    "545" : [ 65, "GIB", 1, 53, "GIB", 3 ],
    "259" : [ 75, "GIB", 5, 69, "GPE", 7 ],
    "27" : [ 8, "OB", 0, 0, "This", 1 ],
    "413" : [ 100, "GIB", 11, 106, "GPE", 5 ],
    "641" : [ 123, "GIB", 0, 122, "GIB", 2 ],
    "71" : [ 21, "GPE", 0, 27, "GIB", 4 ],
    "391" : [ 110, "GIB", 5, 104, "GPE", 7 ],
    "12" : [ 0, "This", 4, 127, "IB", 0 ],
    "445" : [ 111, "GIB", 10, 117, "GPE", 1 ],
    "382" : [ 95, "GPE", 0, 100, "GIB", 5 ],
    "54" : [ 25, "GIB", 6, 20, "GPE", 6 ],
    "572" : [ 63, "GIB", 3, 75, "GIB", 1 ],
    "313" : [ 76, "GIB", 10, 82, "GPE", 1 ],
    "611" : [ 100, "GIB", 0, 99, "GIB", 2 ],
    "144" : [ 37, "GIB", 7, 44, "GPE", 0 ],
    "713" : [ 108, "LSU", 0, 113, "GIB", 5 ],
    "498" : [ 25, "GIB", 2, 26, "GIB", 0 ],
    "49" : [ 14, "GIB", 8, 20, "GPE", 1 ],
    "466" : [ 118, "GPE", 0, 123, "GIB", 5 ],
    "335" : [ 83, "GPE", 0, 89, "GIB", 4 ],
    "236" : [ 59, "GPE", 0, 52, "GIB", 6 ],
    "181" : [ 41, "GIB", 8, 47, "GPE", 1 ],
    "704" : [ 96, "LSU", 0, 89, "GIB", 6 ],
    "350" : [ 98, "GIB", 6, 93, "GPE", 2 ],
    "540" : [ 40, "GIB", 3, 52, "GIB", 1 ],
    "86" : [ 28, "GIB", 6, 23, "GPE", 2 ],
    "159" : [ 51, "GIB", 4, 45, "GPE", 3 ],
    "672" : [ 48, "LSU", 0, 41, "GIB", 6 ],
    "604" : [ 86, "GIB", 3, 98, "GIB", 1 ],
    "187" : [ 53, "GIB", 5, 47, "GPE", 7 ],
    "406" : [ 105, "GPE", 0, 110, "GIB", 5 ],
    "172" : [ 39, "GIB", 9, 46, "GPE", 4 ],
    "113" : [ 27, "GIB", 11, 33, "GPE", 5 ],
    "681" : [ 60, "LSU", 0, 65, "GIB", 5 ],
    "219" : [ 64, "GIB", 4, 58, "GPE", 3 ],
    "274" : [ 70, "GPE", 0, 75, "GIB", 5 ],
    "419" : [ 106, "GPE", 0, 112, "GIB", 4 ],
    "81" : [ 22, "GPE", 0, 16, "GIB", 7 ],
    "377" : [ 89, "GIB", 9, 95, "GPE", 5 ],
    "230" : [ 64, "GIB", 6, 59, "GPE", 2 ],
    "362" : [ 99, "GIB", 6, 94, "GPE", 2 ],
    "451" : [ 123, "GIB", 5, 117, "GPE", 7 ],
    "76" : [ 15, "GIB", 7, 22, "GPE", 4 ],
    "567" : [ 74, "GIB", 0, 73, "GIB", 2 ],
    "7" : [ 3, "IB", 0, 15, "GIB", 5 ],
    "245" : [ 62, "GIB", 11, 68, "GPE", 5 ],
    "318" : [ 87, "GIB", 7, 82, "GPE", 6 ],
    "509" : [ 41, "GIB", 1, 29, "GIB", 3 ],
    "39" : [ 134, "OB", 0, 0, "This", 5 ],
    "649" : [ 124, "GIB", 2, 125, "GIB", 0 ],
    "434" : [ 121, "GIB", 5, 116, "GPE", 2 ],
    "98" : [ 37, "GIB", 5, 32, "GPE", 2 ],
    "616" : [ 89, "GIB", 3, 101, "GIB", 1 ],
    "303" : [ 87, "GIB", 4, 81, "GPE", 3 ],
    "271" : [ 76, "GIB", 5, 70, "GPE", 7 ],
    "208" : [ 50, "GIB", 9, 57, "GPE", 4 ],
    "599" : [ 101, "GIB", 1, 89, "GIB", 3 ],
    "477" : [ 119, "GPE", 0, 113, "GIB", 7 ],
    "387" : [ 110, "GIB", 4, 104, "GPE", 3 ],
    "494" : [ 37, "GIB", 1, 25, "GIB", 3 ],
    "631" : [ 124, "GIB", 1, 112, "GIB", 3 ],
    "345" : [ 92, "GPE", 0, 86, "GIB", 7 ],
    "367" : [ 100, "GIB", 5, 94, "GPE", 7 ],
    "552" : [ 61, "GIB", 2, 62, "GIB", 0 ],
    "535" : [ 51, "GIB", 0, 50, "GIB", 2 ],
    "103" : [ 38, "GIB", 5, 32, "GPE", 7 ],
    "609" : [ 111, "GIB", 1, 99, "GIB", 3 ],
    "323" : [ 82, "GPE", 0, 88, "GIB", 4 ],
    "594" : [ 76, "GIB", 3, 88, "GIB", 1 ],
    "140" : [ 35, "GPE", 0, 28, "GIB", 6 ],
    "213" : [ 57, "GPE", 0, 51, "GIB", 7 ],
    "621" : [ 110, "GIB", 0, 109, "GIB", 2 ],
    "91" : [ 29, "GIB", 5, 23, "GPE", 7 ],
    "483" : [ 13, "GIB", 2, 14, "GIB", 0 ],
    "700" : [ 91, "LSU", 0, 85, "GIB", 7 ],
    "520" : [ 38, "GIB", 2, 39, "GIB", 0 ],
    "66" : [ 26, "GIB", 7, 21, "GPE", 6 ],
    "240" : [ 61, "GIB", 7, 68, "GPE", 0 ],
    "251" : [ 68, "GPE", 0, 74, "GIB", 4 ],
    "626" : [ 99, "GIB", 3, 111, "GIB", 1 ],
    "668" : [ 43, "LSU", 0, 37, "GIB", 7 ],
    "155" : [ 44, "GPE", 0, 50, "GIB", 4 ],
    "198" : [ 61, "GIB", 6, 56, "GPE", 6 ],
    "108" : [ 26, "GIB", 8, 33, "GPE", 0 ],
    "330" : [ 88, "GIB", 7, 83, "GPE", 6 ],
    "462" : [ 123, "GIB", 7, 118, "GPE", 6 ],
    "685" : [ 67, "LSU", 0, 73, "GIB", 4 ],
    "521" : [ 40, "GIB", 0, 39, "GIB", 2 ],
    "130" : [ 34, "GPE", 0, 39, "GIB", 5 ],
    "399" : [ 111, "GIB", 4, 105, "GPE", 3 ],
    "636" : [ 112, "GIB", 2, 113, "GIB", 0 ],
    "695" : [ 89, "GIB", 6, 84, "LSU", 1 ],
    "278" : [ 76, "GIB", 6, 71, "GPE", 2 ],
    "455" : [ 117, "GPE", 0, 123, "GIB", 4 ],
    "223" : [ 64, "GIB", 5, 58, "GPE", 7 ],
    "608" : [ 87, "GIB", 3, 99, "GIB", 1 ],
    "394" : [ 104, "GPE", 0, 109, "GIB", 5 ],
    "306" : [ 86, "GIB", 7, 81, "GPE", 6 ],
    "135" : [ 41, "GIB", 4, 35, "GPE", 3 ],
    "563" : [ 77, "GIB", 1, 65, "GIB", 3 ],
    "299" : [ 80, "GPE", 0, 86, "GIB", 4 ],
    "226" : [ 58, "GPE", 0, 63, "GIB", 5 ],
    "3" : [ 0, "This", 1, 2, "IB", 0 ],
    "267" : [ 76, "GIB", 4, 70, "GPE", 3 ],
    "505" : [ 40, "GIB", 1, 28, "GIB", 3 ],
    "438" : [ 121, "GIB", 6, 116, "GPE", 6 ],
    "431" : [ 107, "GPE", 0, 113, "GIB", 4 ],
    "241" : [ 62, "GIB", 10, 68, "GPE", 1 ],
    "80" : [ 22, "GPE", 0, 15, "GIB", 6 ],
    "653" : [ 19, "LSU", 0, 25, "GIB", 4 ],
    "167" : [ 45, "GPE", 0, 51, "GIB", 4 ],
    "35" : [ 17, "GIB", 4, 10, "OB", 1 ],
    "658" : [ 25, "GIB", 9, 31, "LSU", 0 ],
    "473" : [ 113, "GIB", 9, 119, "GPE", 5 ],
    "490" : [ 17, "GIB", 0, 16, "GIB", 2 ],
    "675" : [ 61, "GIB", 4, 55, "LSU", 1 ],
    "426" : [ 112, "GIB", 7, 107, "GPE", 6 ],
    "589" : [ 87, "GIB", 0, 86, "GIB", 2 ],
    "162" : [ 50, "GIB", 7, 45, "GPE", 6 ],
    "531" : [ 50, "GIB", 0, 49, "GIB", 2 ],
    "680" : [ 60, "LSU", 0, 53, "GIB", 6 ],
    "663" : [ 41, "GIB", 6, 36, "LSU", 1 ],
    "548" : [ 73, "GIB", 1, 61, "GIB", 3 ],
    "374" : [ 100, "GIB", 6, 95, "GPE", 2 ],
    "255" : [ 75, "GIB", 4, 69, "GPE", 3 ],
    "648" : [ 113, "GIB", 3, 125, "GIB", 1 ],
    "209" : [ 51, "GIB", 11, 57, "GPE", 5 ],
    "487" : [ 16, "GIB", 0, 15, "GIB", 2 ],
    "112" : [ 26, "GIB", 9, 33, "GPE", 4 ],
    "617" : [ 113, "GIB", 1, 101, "GIB", 3 ],
    "516" : [ 37, "GIB", 2, 38, "GIB", 0 ],
    "342" : [ 97, "GIB", 6, 92, "GPE", 6 ],
    "123" : [ 40, "GIB", 4, 34, "GPE", 3 ],
    "355" : [ 99, "GIB", 5, 93, "GPE", 7 ],
    "553" : [ 63, "GIB", 0, 62, "GIB", 2 ],
    "458" : [ 123, "GIB", 6, 118, "GPE", 2 ],
    "194" : [ 61, "GIB", 5, 56, "GPE", 2 ],
    "145" : [ 38, "GIB", 10, 44, "GPE", 1 ],
    "48" : [ 13, "GIB", 5, 20, "GPE", 0 ],
    "525" : [ 41, "GIB", 0, 40, "GIB", 2 ],
    "712" : [ 108, "LSU", 0, 101, "GIB", 6 ],
    "557" : [ 64, "GIB", 0, 63, "GIB", 2 ],
    "580" : [ 65, "GIB", 3, 77, "GIB", 1 ],
    "690" : [ 73, "GIB", 9, 79, "LSU", 0 ],
    "63" : [ 27, "GIB", 4, 21, "GPE", 3 ],
    "640" : [ 121, "GIB", 2, 122, "GIB", 0 ],
    "295" : [ 86, "GIB", 5, 80, "GPE", 7 ],
    "18" : [ 0, "This", 6, 129, "IB", 0 ],
    "705" : [ 96, "LSU", 0, 101, "GIB", 5 ],
    "282" : [ 76, "GIB", 7, 71, "GPE", 6 ],
    "150" : [ 49, "GIB", 6, 44, "GPE", 6 ],
    "707" : [ 109, "GIB", 4, 103, "LSU", 1 ],
    "414" : [ 111, "GIB", 7, 106, "GPE", 6 ],
    "95" : [ 23, "GPE", 0, 29, "GIB", 4 ],
    "327" : [ 89, "GIB", 4, 83, "GPE", 3 ],
    "409" : [ 100, "GIB", 10, 106, "GPE", 1 ],
    "263" : [ 69, "GPE", 0, 75, "GIB", 4 ],
    "310" : [ 81, "GPE", 0, 86, "GIB", 5 ],
    "50" : [ 25, "GIB", 5, 20, "GPE", 2 ],
    "67" : [ 27, "GIB", 5, 21, "GPE", 7 ],
    "199" : [ 62, "GIB", 5, 56, "GPE", 7 ],
    "673" : [ 48, "LSU", 0, 53, "GIB", 5 ],
    "177" : [ 46, "GPE", 0, 40, "GIB", 7 ],
    "182" : [ 52, "GIB", 6, 47, "GPE", 2 ],
    "331" : [ 89, "GIB", 5, 83, "GPE", 7 ],
    "441" : [ 116, "GPE", 0, 110, "GIB", 7 ],
    "16" : [ 128, "IB", 0, 122, "GIB", 6 ],
    "585" : [ 86, "GIB", 0, 85, "GIB", 2 ],
    "370" : [ 94, "GPE", 0, 99, "GIB", 5 ],
    "717" : [ 115, "LSU", 0, 121, "GIB", 4 ],
    "502" : [ 26, "GIB", 2, 27, "GIB", 0 ],
    "463" : [ 124, "GIB", 5, 118, "GPE", 7 ],
    "127" : [ 40, "GIB", 5, 34, "GPE", 7 ],
    "338" : [ 97, "GIB", 5, 92, "GPE", 2 ],
    "470" : [ 124, "GIB", 6, 119, "GPE", 2 ],
    "576" : [ 64, "GIB", 3, 76, "GIB", 1 ],
    "359" : [ 93, "GPE", 0, 99, "GIB", 4 ],
    "643" : [ 122, "GIB", 2, 123, "GIB", 0 ],
    "544" : [ 41, "GIB", 3, 53, "GIB", 1 ],
    "31" : [ 15, "GIB", 5, 9, "OB", 0 ],
    "336" : [ 85, "GIB", 7, 92, "GPE", 0 ],
    "703" : [ 101, "GIB", 6, 96, "LSU", 1 ],
    "656" : [ 24, "LSU", 0, 17, "GIB", 5 ],
    "613" : [ 112, "GIB", 1, 100, "GIB", 3 ],
    "154" : [ 44, "GPE", 0, 49, "GIB", 5 ],
    "600" : [ 88, "GIB", 2, 89, "GIB", 0 ],
    "11" : [ 4, "IB", 0, 17, "GIB", 4 ],
    "72" : [ 15, "GIB", 6, 22, "GPE", 0 ],
    "175" : [ 52, "GIB", 5, 46, "GPE", 7 ],
    "386" : [ 109, "GIB", 5, 104, "GPE", 2 ],
    "314" : [ 87, "GIB", 6, 82, "GPE", 2 ],
    "446" : [ 122, "GIB", 6, 117, "GPE", 2 ],
    "571" : [ 75, "GIB", 0, 74, "GIB", 2 ],
    "595" : [ 100, "GIB", 1, 88, "GIB", 3 ],
    "612" : [ 88, "GIB", 3, 100, "GIB", 1 ],
    "143" : [ 35, "GPE", 0, 41, "GIB", 4 ],
    "497" : [ 38, "GIB", 1, 26, "GIB", 3 ],
    "43" : [ 123, "GIB", 8, 135, "OB", 0 ],
    "250" : [ 68, "GPE", 0, 73, "GIB", 5 ],
    "465" : [ 118, "GPE", 0, 112, "GIB", 7 ],
    "231" : [ 65, "GIB", 4, 59, "GPE", 3 ],
    "627" : [ 123, "GIB", 1, 111, "GIB", 3 ],
    "450" : [ 122, "GIB", 7, 117, "GPE", 6 ],
    "99" : [ 38, "GIB", 4, 32, "GPE", 3 ],
    "363" : [ 100, "GIB", 4, 94, "GPE", 3 ],
    "556" : [ 62, "GIB", 2, 63, "GIB", 0 ],
    "539" : [ 52, "GIB", 0, 51, "GIB", 2 ],
    "87" : [ 29, "GIB", 4, 23, "GPE", 3 ],
    "482" : [ 26, "GIB", 1, 14, "GIB", 3 ],
    "203" : [ 56, "GPE", 0, 62, "GIB", 4 ],
    "671" : [ 53, "GIB", 6, 48, "LSU", 1 ],
    "688" : [ 72, "LSU", 0, 65, "GIB", 6 ],
    "524" : [ 39, "GIB", 2, 40, "GIB", 0 ],
    "581" : [ 89, "GIB", 1, 77, "GIB", 3 ],
    "495" : [ 26, "GIB", 0, 25, "GIB", 2 ],
    "218" : [ 63, "GIB", 6, 58, "GPE", 2 ],
    "104" : [ 32, "GPE", 0, 25, "GIB", 6 ],
    "368" : [ 94, "GPE", 0, 87, "GIB", 6 ],
    "588" : [ 85, "GIB", 2, 86, "GIB", 0 ],
    "699" : [ 97, "GIB", 4, 91, "LSU", 1 ],
    "517" : [ 39, "GIB", 0, 38, "GIB", 2 ],
    "319" : [ 88, "GIB", 5, 82, "GPE", 7 ],
    "40" : [ 122, "GIB", 8, 134, "OB", 0 ],
    "304" : [ 74, "GIB", 9, 81, "GPE", 4 ],
    "26" : [ 14, "GIB", 4, 7, "OB", 1 ],
    "258" : [ 74, "GIB", 7, 69, "GPE", 6 ],
    "158" : [ 50, "GIB", 6, 45, "GPE", 2 ],
    "652" : [ 19, "LSU", 0, 13, "GIB", 7 ],
    "351" : [ 99, "GIB", 4, 93, "GPE", 3 ],
    "390" : [ 109, "GIB", 6, 104, "GPE", 6 ],
    "186" : [ 52, "GIB", 7, 47, "GPE", 6 ],
    "55" : [ 26, "GIB", 5, 20, "GPE", 7 ],
    "114" : [ 38, "GIB", 7, 33, "GPE", 6 ],
    "632" : [ 111, "GIB", 2, 112, "GIB", 0 ],
    "401" : [ 99, "GIB", 11, 105, "GPE", 5 ],
    "171" : [ 52, "GIB", 4, 46, "GPE", 3 ],
    "139" : [ 41, "GIB", 5, 35, "GPE", 7 ],
    "418" : [ 106, "GPE", 0, 111, "GIB", 5 ],
    "23" : [ 130, "IB", 0, 125, "GIB", 6 ],
    "8" : [ 3, "IB", 0, 16, "GIB", 4 ],
    "75" : [ 28, "GIB", 4, 22, "GPE", 3 ],
    "568" : [ 62, "GIB", 3, 74, "GIB", 1 ],
    "290" : [ 85, "GIB", 5, 80, "GPE", 2 ],
    "119" : [ 33, "GPE", 0, 39, "GIB", 4 ],
    "58" : [ 20, "GPE", 0, 25, "GIB", 5 ],
    "378" : [ 100, "GIB", 7, 95, "GPE", 6 ],
    "235" : [ 65, "GIB", 5, 59, "GPE", 7 ],
    "246" : [ 73, "GIB", 6, 68, "GPE", 6 ],
    "433" : [ 110, "GIB", 10, 116, "GPE", 1 ],
    "510" : [ 28, "GIB", 2, 29, "GIB", 0 ],
    "207" : [ 63, "GIB", 4, 57, "GPE", 3 ],
    "667" : [ 49, "GIB", 4, 43, "LSU", 1 ],
    "478" : [ 119, "GPE", 0, 124, "GIB", 5 ],
    "272" : [ 70, "GPE", 0, 63, "GIB", 6 ],
    "383" : [ 95, "GPE", 0, 101, "GIB", 4 ],
    "684" : [ 67, "LSU", 0, 61, "GIB", 7 ],
    "346" : [ 92, "GPE", 0, 97, "GIB", 5 ],
    "549" : [ 62, "GIB", 0, 61, "GIB", 2 ],
    "536" : [ 39, "GIB", 3, 51, "GIB", 1 ],
    "82" : [ 22, "GPE", 0, 27, "GIB", 5 ],
    "716" : [ 115, "LSU", 0, 109, "GIB", 7 ],
    "214" : [ 57, "GPE", 0, 62, "GIB", 5 ],
    "287" : [ 71, "GPE", 0, 77, "GIB", 4 ],
    "151" : [ 50, "GIB", 5, 44, "GPE", 7 ],
    "300" : [ 74, "GIB", 8, 81, "GPE", 0 ],
    "620" : [ 121, "GIB", 1, 109, "GIB", 3 ],
    "447" : [ 123, "GIB", 4, 117, "GPE", 3 ],
    "315" : [ 88, "GIB", 4, 82, "GPE", 3 ],
    "432" : [ 109, "GIB", 7, 116, "GPE", 0 ],
    "410" : [ 111, "GIB", 6, 106, "GPE", 2 ],
    "36" : [ 133, "OB", 0, 0, "This", 4 ],
    "168" : [ 39, "GIB", 8, 46, "GPE", 0 ],
    "262" : [ 69, "GPE", 0, 74, "GIB", 5 ],
    "146" : [ 49, "GIB", 5, 44, "GPE", 2 ],
    "30" : [ 9, "OB", 0, 0, "This", 2 ],
    "51" : [ 26, "GIB", 4, 20, "GPE", 3 ],
    "405" : [ 105, "GPE", 0, 99, "GIB", 7 ],
    "190" : [ 47, "GPE", 0, 52, "GIB", 5 ],
    "183" : [ 53, "GIB", 4, 47, "GPE", 3 ],
    "19" : [ 129, "IB", 0, 123, "GIB", 6 ],
    "422" : [ 112, "GIB", 6, 107, "GPE", 2 ],
    "273" : [ 70, "GPE", 0, 64, "GIB", 7 ],
    "373" : [ 89, "GIB", 8, 95, "GPE", 1 ],
    "603" : [ 98, "GIB", 0, 97, "GIB", 2 ],
    "564" : [ 64, "GIB", 2, 65, "GIB", 0 ],
    "305" : [ 75, "GIB", 11, 81, "GPE", 5 ],
    "210" : [ 62, "GIB", 7, 57, "GPE", 6 ],
    "326" : [ 88, "GIB", 6, 83, "GPE", 2 ],
    "107" : [ 32, "GPE", 0, 38, "GIB", 4 ],
    "239" : [ 59, "GPE", 0, 65, "GIB", 4 ],
    "242" : [ 73, "GIB", 5, 68, "GPE", 2 ],
    "4" : [ 2, "IB", 0, 14, "GIB", 5 ],
    "294" : [ 85, "GIB", 6, 80, "GPE", 6 ],
    "126" : [ 39, "GIB", 7, 34, "GPE", 6 ],
    "136" : [ 28, "GIB", 9, 35, "GPE", 4 ],
    "341" : [ 86, "GIB", 11, 92, "GPE", 5 ],
    "506" : [ 27, "GIB", 2, 28, "GIB", 0 ],
    "268" : [ 63, "GIB", 9, 70, "GPE", 4 ],
    "358" : [ 93, "GPE", 0, 98, "GIB", 5 ],
    "79" : [ 28, "GIB", 5, 22, "GPE", 7 ],
    "195" : [ 62, "GIB", 4, 56, "GPE", 3 ],
    "437" : [ 110, "GIB", 11, 116, "GPE", 5 ],
    "474" : [ 124, "GIB", 7, 119, "GPE", 6 ],
    "664" : [ 36, "LSU", 0, 29, "GIB", 6 ],
    "400" : [ 98, "GIB", 9, 105, "GPE", 4 ],
    "635" : [ 125, "GIB", 1, 113, "GIB", 3 ],
    "532" : [ 38, "GIB", 3, 50, "GIB", 1 ],
    "696" : [ 84, "LSU", 0, 77, "GIB", 6 ],
    "720" : [ 120, "LSU", 0, 113, "GIB", 6 ],
    "94" : [ 23, "GPE", 0, 28, "GIB", 5 ],
    "283" : [ 77, "GIB", 5, 71, "GPE", 7 ],
    "415" : [ 112, "GIB", 5, 106, "GPE", 7 ],
    "395" : [ 104, "GPE", 0, 110, "GIB", 4 ],
    "624" : [ 109, "GIB", 2, 110, "GIB", 0 ],
    "464" : [ 118, "GPE", 0, 111, "GIB", 6 ],
    "332" : [ 83, "GPE", 0, 76, "GIB", 6 ],
    "575" : [ 76, "GIB", 0, 75, "GIB", 2 ],
    "427" : [ 113, "GIB", 5, 107, "GPE", 7 ],
    "596" : [ 87, "GIB", 2, 88, "GIB", 0 ],
    "528" : [ 40, "GIB", 2, 41, "GIB", 0 ],
    "644" : [ 124, "GIB", 0, 123, "GIB", 2 ],
    "459" : [ 124, "GIB", 4, 118, "GPE", 3 ],
    "131" : [ 34, "GPE", 0, 40, "GIB", 4 ],
    "47" : [ 125, "GIB", 7, 136, "OB", 1 ],
    "15" : [ 0, "This", 5, 128, "IB", 0 ],
    "163" : [ 51, "GIB", 5, 45, "GPE", 7 ],
    "200" : [ 56, "GPE", 0, 49, "GIB", 6 ],
    "68" : [ 21, "GPE", 0, 14, "GIB", 6 ],
    "62" : [ 26, "GIB", 6, 21, "GPE", 2 ],
    "178" : [ 46, "GPE", 0, 51, "GIB", 5 ],
    "277" : [ 65, "GIB", 8, 71, "GPE", 1 ],
    "691" : [ 85, "GIB", 4, 79, "LSU", 1 ],
    "442" : [ 116, "GPE", 0, 121, "GIB", 5 ],
    "501" : [ 39, "GIB", 1, 27, "GIB", 3 ],
    "369" : [ 94, "GPE", 0, 88, "GIB", 7 ],
    "607" : [ 99, "GIB", 0, 98, "GIB", 2 ],
    "90" : [ 28, "GIB", 7, 23, "GPE", 6 ],
    "111" : [ 39, "GIB", 4, 33, "GPE", 3 ],
    "254" : [ 74, "GIB", 6, 69, "GPE", 2 ],
    "227" : [ 58, "GPE", 0, 64, "GIB", 4 ],
    "322" : [ 82, "GPE", 0, 87, "GIB", 5 ],
    "486" : [ 14, "GIB", 2, 15, "GIB", 0 ],
    "337" : [ 86, "GIB", 10, 92, "GPE", 1 ],
    "122" : [ 39, "GIB", 6, 34, "GPE", 2 ],
    "469" : [ 113, "GIB", 8, 119, "GPE", 1 ],
    "354" : [ 98, "GIB", 7, 93, "GPE", 6 ],
    "83" : [ 22, "GPE", 0, 28, "GIB", 4 ],
    "309" : [ 81, "GPE", 0, 75, "GIB", 7 ],
    "659" : [ 37, "GIB", 4, 31, "LSU", 1 ],
    "543" : [ 53, "GIB", 0, 52, "GIB", 2 ],
    "215" : [ 57, "GPE", 0, 63, "GIB", 4 ],
    "560" : [ 63, "GIB", 2, 64, "GIB", 0 ],
    "639" : [ 110, "GIB", 3, 122, "GIB", 1 ],
    "676" : [ 55, "LSU", 0, 49, "GIB", 7 ],
    "491" : [ 29, "GIB", 1, 17, "GIB", 3 ],
    "222" : [ 63, "GIB", 7, 58, "GPE", 6 ],
    "592" : [ 86, "GIB", 2, 87, "GIB", 0 ],
    "496" : [ 14, "GIB", 3, 26, "GIB", 1 ],
    "454" : [ 117, "GPE", 0, 122, "GIB", 5 ],
    "364" : [ 87, "GIB", 9, 94, "GPE", 4 ],
    "708" : [ 103, "LSU", 0, 97, "GIB", 7 ],
    "232" : [ 52, "GIB", 9, 59, "GPE", 4 ],
    "100" : [ 25, "GIB", 8, 32, "GPE", 4 ]
  },
  "max_delay" : 4
}